[{"name":"im_flutter_sdk","qualifiedName":"im_flutter_sdk","href":"im_flutter_sdk/im_flutter_sdk-library.html","type":"library","overriddenDepth":0},{"name":"EMChatManager","qualifiedName":"im_flutter_sdk.EMChatManager","href":"im_flutter_sdk/EMChatManager-class.html","type":"class","overriddenDepth":0,"enclosedBy":{"name":"im_flutter_sdk","type":"library"}},{"name":"operator ==","qualifiedName":"im_flutter_sdk.EMChatManager.==","href":"im_flutter_sdk/EMChatManager/operator_equals.html","type":"method","overriddenDepth":0,"enclosedBy":{"name":"EMChatManager","type":"class"}},{"name":"addMessageListener","qualifiedName":"im_flutter_sdk.EMChatManager.addMessageListener","href":"im_flutter_sdk/EMChatManager/addMessageListener.html","type":"method","overriddenDepth":0,"enclosedBy":{"name":"EMChatManager","type":"class"}},{"name":"deleteConversation","qualifiedName":"im_flutter_sdk.EMChatManager.deleteConversation","href":"im_flutter_sdk/EMChatManager/deleteConversation.html","type":"method","overriddenDepth":0,"enclosedBy":{"name":"EMChatManager","type":"class"}},{"name":"getAllConversations","qualifiedName":"im_flutter_sdk.EMChatManager.getAllConversations","href":"im_flutter_sdk/EMChatManager/getAllConversations.html","type":"method","overriddenDepth":0,"enclosedBy":{"name":"EMChatManager","type":"class"}},{"name":"getConversation","qualifiedName":"im_flutter_sdk.EMChatManager.getConversation","href":"im_flutter_sdk/EMChatManager/getConversation.html","type":"method","overriddenDepth":0,"enclosedBy":{"name":"EMChatManager","type":"class"}},{"name":"getMessage","qualifiedName":"im_flutter_sdk.EMChatManager.getMessage","href":"im_flutter_sdk/EMChatManager/getMessage.html","type":"method","overriddenDepth":0,"enclosedBy":{"name":"EMChatManager","type":"class"}},{"name":"getUnreadMessageCount","qualifiedName":"im_flutter_sdk.EMChatManager.getUnreadMessageCount","href":"im_flutter_sdk/EMChatManager/getUnreadMessageCount.html","type":"method","overriddenDepth":0,"enclosedBy":{"name":"EMChatManager","type":"class"}},{"name":"hashCode","qualifiedName":"im_flutter_sdk.EMChatManager.hashCode","href":"im_flutter_sdk/EMChatManager/hashCode.html","type":"property","overriddenDepth":0,"enclosedBy":{"name":"EMChatManager","type":"class"}},{"name":"loadAllConversations","qualifiedName":"im_flutter_sdk.EMChatManager.loadAllConversations","href":"im_flutter_sdk/EMChatManager/loadAllConversations.html","type":"method","overriddenDepth":0,"enclosedBy":{"name":"EMChatManager","type":"class"}},{"name":"noSuchMethod","qualifiedName":"im_flutter_sdk.EMChatManager.noSuchMethod","href":"im_flutter_sdk/EMChatManager/noSuchMethod.html","type":"method","overriddenDepth":0,"enclosedBy":{"name":"EMChatManager","type":"class"}},{"name":"onConversationUpdate","qualifiedName":"im_flutter_sdk.EMChatManager.onConversationUpdate","href":"im_flutter_sdk/EMChatManager/onConversationUpdate.html","type":"method","overriddenDepth":0,"enclosedBy":{"name":"EMChatManager","type":"class"}},{"name":"removeMessageListener","qualifiedName":"im_flutter_sdk.EMChatManager.removeMessageListener","href":"im_flutter_sdk/EMChatManager/removeMessageListener.html","type":"method","overriddenDepth":0,"enclosedBy":{"name":"EMChatManager","type":"class"}},{"name":"runtimeType","qualifiedName":"im_flutter_sdk.EMChatManager.runtimeType","href":"im_flutter_sdk/EMChatManager/runtimeType.html","type":"property","overriddenDepth":0,"enclosedBy":{"name":"EMChatManager","type":"class"}},{"name":"sendMessage","qualifiedName":"im_flutter_sdk.EMChatManager.sendMessage","href":"im_flutter_sdk/EMChatManager/sendMessage.html","type":"method","overriddenDepth":0,"enclosedBy":{"name":"EMChatManager","type":"class"}},{"name":"toString","qualifiedName":"im_flutter_sdk.EMChatManager.toString","href":"im_flutter_sdk/EMChatManager/toString.html","type":"method","overriddenDepth":0,"enclosedBy":{"name":"EMChatManager","type":"class"}},{"name":"EMChatRoom","qualifiedName":"im_flutter_sdk.EMChatRoom","href":"im_flutter_sdk/EMChatRoom-class.html","type":"class","overriddenDepth":0,"enclosedBy":{"name":"im_flutter_sdk","type":"library"}},{"name":"operator ==","qualifiedName":"im_flutter_sdk.EMChatRoom.==","href":"im_flutter_sdk/EMChatRoom/operator_equals.html","type":"method","overriddenDepth":0,"enclosedBy":{"name":"EMChatRoom","type":"class"}},{"name":"getAdminList","qualifiedName":"im_flutter_sdk.EMChatRoom.getAdminList","href":"im_flutter_sdk/EMChatRoom/getAdminList.html","type":"method","overriddenDepth":0,"enclosedBy":{"name":"EMChatRoom","type":"class"}},{"name":"getAnnouncement","qualifiedName":"im_flutter_sdk.EMChatRoom.getAnnouncement","href":"im_flutter_sdk/EMChatRoom/getAnnouncement.html","type":"method","overriddenDepth":0,"enclosedBy":{"name":"EMChatRoom","type":"class"}},{"name":"getDescription","qualifiedName":"im_flutter_sdk.EMChatRoom.getDescription","href":"im_flutter_sdk/EMChatRoom/getDescription.html","type":"method","overriddenDepth":0,"enclosedBy":{"name":"EMChatRoom","type":"class"}},{"name":"getId","qualifiedName":"im_flutter_sdk.EMChatRoom.getId","href":"im_flutter_sdk/EMChatRoom/getId.html","type":"method","overriddenDepth":0,"enclosedBy":{"name":"EMChatRoom","type":"class"}},{"name":"getMaxUsers","qualifiedName":"im_flutter_sdk.EMChatRoom.getMaxUsers","href":"im_flutter_sdk/EMChatRoom/getMaxUsers.html","type":"method","overriddenDepth":0,"enclosedBy":{"name":"EMChatRoom","type":"class"}},{"name":"getMemberList","qualifiedName":"im_flutter_sdk.EMChatRoom.getMemberList","href":"im_flutter_sdk/EMChatRoom/getMemberList.html","type":"method","overriddenDepth":0,"enclosedBy":{"name":"EMChatRoom","type":"class"}},{"name":"getName","qualifiedName":"im_flutter_sdk.EMChatRoom.getName","href":"im_flutter_sdk/EMChatRoom/getName.html","type":"method","overriddenDepth":0,"enclosedBy":{"name":"EMChatRoom","type":"class"}},{"name":"getOwner","qualifiedName":"im_flutter_sdk.EMChatRoom.getOwner","href":"im_flutter_sdk/EMChatRoom/getOwner.html","type":"method","overriddenDepth":0,"enclosedBy":{"name":"EMChatRoom","type":"class"}},{"name":"getPermissionType","qualifiedName":"im_flutter_sdk.EMChatRoom.getPermissionType","href":"im_flutter_sdk/EMChatRoom/getPermissionType.html","type":"method","overriddenDepth":0,"enclosedBy":{"name":"EMChatRoom","type":"class"}},{"name":"hashCode","qualifiedName":"im_flutter_sdk.EMChatRoom.hashCode","href":"im_flutter_sdk/EMChatRoom/hashCode.html","type":"property","overriddenDepth":0,"enclosedBy":{"name":"EMChatRoom","type":"class"}},{"name":"noSuchMethod","qualifiedName":"im_flutter_sdk.EMChatRoom.noSuchMethod","href":"im_flutter_sdk/EMChatRoom/noSuchMethod.html","type":"method","overriddenDepth":0,"enclosedBy":{"name":"EMChatRoom","type":"class"}},{"name":"runtimeType","qualifiedName":"im_flutter_sdk.EMChatRoom.runtimeType","href":"im_flutter_sdk/EMChatRoom/runtimeType.html","type":"property","overriddenDepth":0,"enclosedBy":{"name":"EMChatRoom","type":"class"}},{"name":"EMChatRoomEventListener","qualifiedName":"im_flutter_sdk.EMChatRoomEventListener","href":"im_flutter_sdk/EMChatRoomEventListener-class.html","type":"class","overriddenDepth":0,"enclosedBy":{"name":"im_flutter_sdk","type":"library"}},{"name":"EMChatRoomEventListener","qualifiedName":"im_flutter_sdk.EMChatRoomEventListener","href":"im_flutter_sdk/EMChatRoomEventListener/EMChatRoomEventListener.html","type":"constructor","overriddenDepth":0,"enclosedBy":{"name":"EMChatRoomEventListener","type":"class"}},{"name":"operator ==","qualifiedName":"im_flutter_sdk.EMChatRoomEventListener.==","href":"im_flutter_sdk/EMChatRoomEventListener/operator_equals.html","type":"method","overriddenDepth":0,"enclosedBy":{"name":"EMChatRoomEventListener","type":"class"}},{"name":"hashCode","qualifiedName":"im_flutter_sdk.EMChatRoomEventListener.hashCode","href":"im_flutter_sdk/EMChatRoomEventListener/hashCode.html","type":"property","overriddenDepth":0,"enclosedBy":{"name":"EMChatRoomEventListener","type":"class"}},{"name":"noSuchMethod","qualifiedName":"im_flutter_sdk.EMChatRoomEventListener.noSuchMethod","href":"im_flutter_sdk/EMChatRoomEventListener/noSuchMethod.html","type":"method","overriddenDepth":0,"enclosedBy":{"name":"EMChatRoomEventListener","type":"class"}},{"name":"onChatRoomDestroyed","qualifiedName":"im_flutter_sdk.EMChatRoomEventListener.onChatRoomDestroyed","href":"im_flutter_sdk/EMChatRoomEventListener/onChatRoomDestroyed.html","type":"method","overriddenDepth":0,"enclosedBy":{"name":"EMChatRoomEventListener","type":"class"}},{"name":"onMemberExited","qualifiedName":"im_flutter_sdk.EMChatRoomEventListener.onMemberExited","href":"im_flutter_sdk/EMChatRoomEventListener/onMemberExited.html","type":"method","overriddenDepth":0,"enclosedBy":{"name":"EMChatRoomEventListener","type":"class"}},{"name":"onMemberJoined","qualifiedName":"im_flutter_sdk.EMChatRoomEventListener.onMemberJoined","href":"im_flutter_sdk/EMChatRoomEventListener/onMemberJoined.html","type":"method","overriddenDepth":0,"enclosedBy":{"name":"EMChatRoomEventListener","type":"class"}},{"name":"onRemovedFromChatRoom","qualifiedName":"im_flutter_sdk.EMChatRoomEventListener.onRemovedFromChatRoom","href":"im_flutter_sdk/EMChatRoomEventListener/onRemovedFromChatRoom.html","type":"method","overriddenDepth":0,"enclosedBy":{"name":"EMChatRoomEventListener","type":"class"}},{"name":"runtimeType","qualifiedName":"im_flutter_sdk.EMChatRoomEventListener.runtimeType","href":"im_flutter_sdk/EMChatRoomEventListener/runtimeType.html","type":"property","overriddenDepth":0,"enclosedBy":{"name":"EMChatRoomEventListener","type":"class"}},{"name":"toString","qualifiedName":"im_flutter_sdk.EMChatRoomEventListener.toString","href":"im_flutter_sdk/EMChatRoomEventListener/toString.html","type":"method","overriddenDepth":0,"enclosedBy":{"name":"EMChatRoomEventListener","type":"class"}},{"name":"EMChatRoomPermissionType","qualifiedName":"im_flutter_sdk.EMChatRoomPermissionType","href":"im_flutter_sdk/EMChatRoomPermissionType-class.html","type":"enum","overriddenDepth":0,"enclosedBy":{"name":"im_flutter_sdk","type":"library"}},{"name":"operator ==","qualifiedName":"im_flutter_sdk.EMChatRoomPermissionType.==","href":"im_flutter_sdk/EMChatRoomPermissionType/operator_equals.html","type":"method","overriddenDepth":0,"enclosedBy":{"name":"EMChatRoomPermissionType","type":"enum"}},{"name":"hashCode","qualifiedName":"im_flutter_sdk.EMChatRoomPermissionType.hashCode","href":"im_flutter_sdk/EMChatRoomPermissionType/hashCode.html","type":"property","overriddenDepth":0,"enclosedBy":{"name":"EMChatRoomPermissionType","type":"enum"}},{"name":"noSuchMethod","qualifiedName":"im_flutter_sdk.EMChatRoomPermissionType.noSuchMethod","href":"im_flutter_sdk/EMChatRoomPermissionType/noSuchMethod.html","type":"method","overriddenDepth":0,"enclosedBy":{"name":"EMChatRoomPermissionType","type":"enum"}},{"name":"runtimeType","qualifiedName":"im_flutter_sdk.EMChatRoomPermissionType.runtimeType","href":"im_flutter_sdk/EMChatRoomPermissionType/runtimeType.html","type":"property","overriddenDepth":0,"enclosedBy":{"name":"EMChatRoomPermissionType","type":"enum"}},{"name":"toString","qualifiedName":"im_flutter_sdk.EMChatRoomPermissionType.toString","href":"im_flutter_sdk/EMChatRoomPermissionType/toString.html","type":"method","overriddenDepth":1,"enclosedBy":{"name":"EMChatRoomPermissionType","type":"enum"}},{"name":"EMClient","qualifiedName":"im_flutter_sdk.EMClient","href":"im_flutter_sdk/EMClient-class.html","type":"class","overriddenDepth":0,"enclosedBy":{"name":"im_flutter_sdk","type":"library"}},{"name":"operator ==","qualifiedName":"im_flutter_sdk.EMClient.==","href":"im_flutter_sdk/EMClient/operator_equals.html","type":"method","overriddenDepth":0,"enclosedBy":{"name":"EMClient","type":"class"}},{"name":"addConnectionListener","qualifiedName":"im_flutter_sdk.EMClient.addConnectionListener","href":"im_flutter_sdk/EMClient/addConnectionListener.html","type":"method","overriddenDepth":0,"enclosedBy":{"name":"EMClient","type":"class"}},{"name":"createAccount","qualifiedName":"im_flutter_sdk.EMClient.createAccount","href":"im_flutter_sdk/EMClient/createAccount.html","type":"method","overriddenDepth":0,"enclosedBy":{"name":"EMClient","type":"class"}},{"name":"getCurrentUser","qualifiedName":"im_flutter_sdk.EMClient.getCurrentUser","href":"im_flutter_sdk/EMClient/getCurrentUser.html","type":"method","overriddenDepth":0,"enclosedBy":{"name":"EMClient","type":"class"}},{"name":"EMClient.getInstance","qualifiedName":"im_flutter_sdk.EMClient.getInstance","href":"im_flutter_sdk/EMClient/EMClient.getInstance.html","type":"constructor","overriddenDepth":0,"enclosedBy":{"name":"EMClient","type":"class"}},{"name":"hashCode","qualifiedName":"im_flutter_sdk.EMClient.hashCode","href":"im_flutter_sdk/EMClient/hashCode.html","type":"property","overriddenDepth":0,"enclosedBy":{"name":"EMClient","type":"class"}},{"name":"init","qualifiedName":"im_flutter_sdk.EMClient.init","href":"im_flutter_sdk/EMClient/init.html","type":"method","overriddenDepth":0,"enclosedBy":{"name":"EMClient","type":"class"}},{"name":"isConnected","qualifiedName":"im_flutter_sdk.EMClient.isConnected","href":"im_flutter_sdk/EMClient/isConnected.html","type":"method","overriddenDepth":0,"enclosedBy":{"name":"EMClient","type":"class"}},{"name":"isLoggedInBefore","qualifiedName":"im_flutter_sdk.EMClient.isLoggedInBefore","href":"im_flutter_sdk/EMClient/isLoggedInBefore.html","type":"method","overriddenDepth":0,"enclosedBy":{"name":"EMClient","type":"class"}},{"name":"login","qualifiedName":"im_flutter_sdk.EMClient.login","href":"im_flutter_sdk/EMClient/login.html","type":"method","overriddenDepth":0,"enclosedBy":{"name":"EMClient","type":"class"}},{"name":"logout","qualifiedName":"im_flutter_sdk.EMClient.logout","href":"im_flutter_sdk/EMClient/logout.html","type":"method","overriddenDepth":0,"enclosedBy":{"name":"EMClient","type":"class"}},{"name":"noSuchMethod","qualifiedName":"im_flutter_sdk.EMClient.noSuchMethod","href":"im_flutter_sdk/EMClient/noSuchMethod.html","type":"method","overriddenDepth":0,"enclosedBy":{"name":"EMClient","type":"class"}},{"name":"removeConnectionListener","qualifiedName":"im_flutter_sdk.EMClient.removeConnectionListener","href":"im_flutter_sdk/EMClient/removeConnectionListener.html","type":"method","overriddenDepth":0,"enclosedBy":{"name":"EMClient","type":"class"}},{"name":"runtimeType","qualifiedName":"im_flutter_sdk.EMClient.runtimeType","href":"im_flutter_sdk/EMClient/runtimeType.html","type":"property","overriddenDepth":0,"enclosedBy":{"name":"EMClient","type":"class"}},{"name":"toString","qualifiedName":"im_flutter_sdk.EMClient.toString","href":"im_flutter_sdk/EMClient/toString.html","type":"method","overriddenDepth":0,"enclosedBy":{"name":"EMClient","type":"class"}},{"name":"updateCurrentUserNick","qualifiedName":"im_flutter_sdk.EMClient.updateCurrentUserNick","href":"im_flutter_sdk/EMClient/updateCurrentUserNick.html","type":"method","overriddenDepth":0,"enclosedBy":{"name":"EMClient","type":"class"}},{"name":"EMCmdMessageBody","qualifiedName":"im_flutter_sdk.EMCmdMessageBody","href":"im_flutter_sdk/EMCmdMessageBody-class.html","type":"class","overriddenDepth":0,"enclosedBy":{"name":"im_flutter_sdk","type":"library"}},{"name":"EMCmdMessageBody","qualifiedName":"im_flutter_sdk.EMCmdMessageBody","href":"im_flutter_sdk/EMCmdMessageBody/EMCmdMessageBody.html","type":"constructor","overriddenDepth":0,"enclosedBy":{"name":"EMCmdMessageBody","type":"class"}},{"name":"operator ==","qualifiedName":"im_flutter_sdk.EMCmdMessageBody.==","href":"im_flutter_sdk/EMCmdMessageBody/operator_equals.html","type":"method","overriddenDepth":0,"enclosedBy":{"name":"EMCmdMessageBody","type":"class"}},{"name":"action","qualifiedName":"im_flutter_sdk.EMCmdMessageBody.action","href":"im_flutter_sdk/EMCmdMessageBody/action.html","type":"property","overriddenDepth":0,"enclosedBy":{"name":"EMCmdMessageBody","type":"class"}},{"name":"deliverOnlineOnly","qualifiedName":"im_flutter_sdk.EMCmdMessageBody.deliverOnlineOnly","href":"im_flutter_sdk/EMCmdMessageBody/deliverOnlineOnly.html","type":"property","overriddenDepth":0,"enclosedBy":{"name":"EMCmdMessageBody","type":"class"}},{"name":"hashCode","qualifiedName":"im_flutter_sdk.EMCmdMessageBody.hashCode","href":"im_flutter_sdk/EMCmdMessageBody/hashCode.html","type":"property","overriddenDepth":0,"enclosedBy":{"name":"EMCmdMessageBody","type":"class"}},{"name":"noSuchMethod","qualifiedName":"im_flutter_sdk.EMCmdMessageBody.noSuchMethod","href":"im_flutter_sdk/EMCmdMessageBody/noSuchMethod.html","type":"method","overriddenDepth":0,"enclosedBy":{"name":"EMCmdMessageBody","type":"class"}},{"name":"runtimeType","qualifiedName":"im_flutter_sdk.EMCmdMessageBody.runtimeType","href":"im_flutter_sdk/EMCmdMessageBody/runtimeType.html","type":"property","overriddenDepth":0,"enclosedBy":{"name":"EMCmdMessageBody","type":"class"}},{"name":"toString","qualifiedName":"im_flutter_sdk.EMCmdMessageBody.toString","href":"im_flutter_sdk/EMCmdMessageBody/toString.html","type":"method","overriddenDepth":0,"enclosedBy":{"name":"EMCmdMessageBody","type":"class"}},{"name":"EMConnectionListener","qualifiedName":"im_flutter_sdk.EMConnectionListener","href":"im_flutter_sdk/EMConnectionListener-class.html","type":"class","overriddenDepth":0,"enclosedBy":{"name":"im_flutter_sdk","type":"library"}},{"name":"EMConnectionListener","qualifiedName":"im_flutter_sdk.EMConnectionListener","href":"im_flutter_sdk/EMConnectionListener/EMConnectionListener.html","type":"constructor","overriddenDepth":0,"enclosedBy":{"name":"EMConnectionListener","type":"class"}},{"name":"operator ==","qualifiedName":"im_flutter_sdk.EMConnectionListener.==","href":"im_flutter_sdk/EMConnectionListener/operator_equals.html","type":"method","overriddenDepth":0,"enclosedBy":{"name":"EMConnectionListener","type":"class"}},{"name":"hashCode","qualifiedName":"im_flutter_sdk.EMConnectionListener.hashCode","href":"im_flutter_sdk/EMConnectionListener/hashCode.html","type":"property","overriddenDepth":0,"enclosedBy":{"name":"EMConnectionListener","type":"class"}},{"name":"noSuchMethod","qualifiedName":"im_flutter_sdk.EMConnectionListener.noSuchMethod","href":"im_flutter_sdk/EMConnectionListener/noSuchMethod.html","type":"method","overriddenDepth":0,"enclosedBy":{"name":"EMConnectionListener","type":"class"}},{"name":"onConnected","qualifiedName":"im_flutter_sdk.EMConnectionListener.onConnected","href":"im_flutter_sdk/EMConnectionListener/onConnected.html","type":"method","overriddenDepth":0,"enclosedBy":{"name":"EMConnectionListener","type":"class"}},{"name":"onDisconnected","qualifiedName":"im_flutter_sdk.EMConnectionListener.onDisconnected","href":"im_flutter_sdk/EMConnectionListener/onDisconnected.html","type":"method","overriddenDepth":0,"enclosedBy":{"name":"EMConnectionListener","type":"class"}},{"name":"runtimeType","qualifiedName":"im_flutter_sdk.EMConnectionListener.runtimeType","href":"im_flutter_sdk/EMConnectionListener/runtimeType.html","type":"property","overriddenDepth":0,"enclosedBy":{"name":"EMConnectionListener","type":"class"}},{"name":"toString","qualifiedName":"im_flutter_sdk.EMConnectionListener.toString","href":"im_flutter_sdk/EMConnectionListener/toString.html","type":"method","overriddenDepth":0,"enclosedBy":{"name":"EMConnectionListener","type":"class"}},{"name":"EMContact","qualifiedName":"im_flutter_sdk.EMContact","href":"im_flutter_sdk/EMContact-class.html","type":"class","overriddenDepth":0,"enclosedBy":{"name":"im_flutter_sdk","type":"library"}},{"name":"EMContact","qualifiedName":"im_flutter_sdk.EMContact","href":"im_flutter_sdk/EMContact/EMContact.html","type":"constructor","overriddenDepth":0,"enclosedBy":{"name":"EMContact","type":"class"}},{"name":"operator ==","qualifiedName":"im_flutter_sdk.EMContact.==","href":"im_flutter_sdk/EMContact/operator_equals.html","type":"method","overriddenDepth":0,"enclosedBy":{"name":"EMContact","type":"class"}},{"name":"hashCode","qualifiedName":"im_flutter_sdk.EMContact.hashCode","href":"im_flutter_sdk/EMContact/hashCode.html","type":"property","overriddenDepth":0,"enclosedBy":{"name":"EMContact","type":"class"}},{"name":"noSuchMethod","qualifiedName":"im_flutter_sdk.EMContact.noSuchMethod","href":"im_flutter_sdk/EMContact/noSuchMethod.html","type":"method","overriddenDepth":0,"enclosedBy":{"name":"EMContact","type":"class"}},{"name":"runtimeType","qualifiedName":"im_flutter_sdk.EMContact.runtimeType","href":"im_flutter_sdk/EMContact/runtimeType.html","type":"property","overriddenDepth":0,"enclosedBy":{"name":"EMContact","type":"class"}},{"name":"toString","qualifiedName":"im_flutter_sdk.EMContact.toString","href":"im_flutter_sdk/EMContact/toString.html","type":"method","overriddenDepth":0,"enclosedBy":{"name":"EMContact","type":"class"}},{"name":"userName","qualifiedName":"im_flutter_sdk.EMContact.userName","href":"im_flutter_sdk/EMContact/userName.html","type":"property","overriddenDepth":0,"enclosedBy":{"name":"EMContact","type":"class"}},{"name":"EMContactEventListener","qualifiedName":"im_flutter_sdk.EMContactEventListener","href":"im_flutter_sdk/EMContactEventListener-class.html","type":"class","overriddenDepth":0,"enclosedBy":{"name":"im_flutter_sdk","type":"library"}},{"name":"EMContactEventListener","qualifiedName":"im_flutter_sdk.EMContactEventListener","href":"im_flutter_sdk/EMContactEventListener/EMContactEventListener.html","type":"constructor","overriddenDepth":0,"enclosedBy":{"name":"EMContactEventListener","type":"class"}},{"name":"operator ==","qualifiedName":"im_flutter_sdk.EMContactEventListener.==","href":"im_flutter_sdk/EMContactEventListener/operator_equals.html","type":"method","overriddenDepth":0,"enclosedBy":{"name":"EMContactEventListener","type":"class"}},{"name":"hashCode","qualifiedName":"im_flutter_sdk.EMContactEventListener.hashCode","href":"im_flutter_sdk/EMContactEventListener/hashCode.html","type":"property","overriddenDepth":0,"enclosedBy":{"name":"EMContactEventListener","type":"class"}},{"name":"noSuchMethod","qualifiedName":"im_flutter_sdk.EMContactEventListener.noSuchMethod","href":"im_flutter_sdk/EMContactEventListener/noSuchMethod.html","type":"method","overriddenDepth":0,"enclosedBy":{"name":"EMContactEventListener","type":"class"}},{"name":"onContactAdded","qualifiedName":"im_flutter_sdk.EMContactEventListener.onContactAdded","href":"im_flutter_sdk/EMContactEventListener/onContactAdded.html","type":"method","overriddenDepth":0,"enclosedBy":{"name":"EMContactEventListener","type":"class"}},{"name":"onContactDeleted","qualifiedName":"im_flutter_sdk.EMContactEventListener.onContactDeleted","href":"im_flutter_sdk/EMContactEventListener/onContactDeleted.html","type":"method","overriddenDepth":0,"enclosedBy":{"name":"EMContactEventListener","type":"class"}},{"name":"onContactInvited","qualifiedName":"im_flutter_sdk.EMContactEventListener.onContactInvited","href":"im_flutter_sdk/EMContactEventListener/onContactInvited.html","type":"method","overriddenDepth":0,"enclosedBy":{"name":"EMContactEventListener","type":"class"}},{"name":"onFriendRequestAccepted","qualifiedName":"im_flutter_sdk.EMContactEventListener.onFriendRequestAccepted","href":"im_flutter_sdk/EMContactEventListener/onFriendRequestAccepted.html","type":"method","overriddenDepth":0,"enclosedBy":{"name":"EMContactEventListener","type":"class"}},{"name":"onFriendRequestDeclined","qualifiedName":"im_flutter_sdk.EMContactEventListener.onFriendRequestDeclined","href":"im_flutter_sdk/EMContactEventListener/onFriendRequestDeclined.html","type":"method","overriddenDepth":0,"enclosedBy":{"name":"EMContactEventListener","type":"class"}},{"name":"runtimeType","qualifiedName":"im_flutter_sdk.EMContactEventListener.runtimeType","href":"im_flutter_sdk/EMContactEventListener/runtimeType.html","type":"property","overriddenDepth":0,"enclosedBy":{"name":"EMContactEventListener","type":"class"}},{"name":"toString","qualifiedName":"im_flutter_sdk.EMContactEventListener.toString","href":"im_flutter_sdk/EMContactEventListener/toString.html","type":"method","overriddenDepth":0,"enclosedBy":{"name":"EMContactEventListener","type":"class"}},{"name":"EMContactManager","qualifiedName":"im_flutter_sdk.EMContactManager","href":"im_flutter_sdk/EMContactManager-class.html","type":"class","overriddenDepth":0,"enclosedBy":{"name":"im_flutter_sdk","type":"library"}},{"name":"operator ==","qualifiedName":"im_flutter_sdk.EMContactManager.==","href":"im_flutter_sdk/EMContactManager/operator_equals.html","type":"method","overriddenDepth":0,"enclosedBy":{"name":"EMContactManager","type":"class"}},{"name":"acceptInvitation","qualifiedName":"im_flutter_sdk.EMContactManager.acceptInvitation","href":"im_flutter_sdk/EMContactManager/acceptInvitation.html","type":"method","overriddenDepth":0,"enclosedBy":{"name":"EMContactManager","type":"class"}},{"name":"addContact","qualifiedName":"im_flutter_sdk.EMContactManager.addContact","href":"im_flutter_sdk/EMContactManager/addContact.html","type":"method","overriddenDepth":0,"enclosedBy":{"name":"EMContactManager","type":"class"}},{"name":"addContactListener","qualifiedName":"im_flutter_sdk.EMContactManager.addContactListener","href":"im_flutter_sdk/EMContactManager/addContactListener.html","type":"method","overriddenDepth":0,"enclosedBy":{"name":"EMContactManager","type":"class"}},{"name":"addUserToBlackList","qualifiedName":"im_flutter_sdk.EMContactManager.addUserToBlackList","href":"im_flutter_sdk/EMContactManager/addUserToBlackList.html","type":"method","overriddenDepth":0,"enclosedBy":{"name":"EMContactManager","type":"class"}},{"name":"declineInvitation","qualifiedName":"im_flutter_sdk.EMContactManager.declineInvitation","href":"im_flutter_sdk/EMContactManager/declineInvitation.html","type":"method","overriddenDepth":0,"enclosedBy":{"name":"EMContactManager","type":"class"}},{"name":"deleteContact","qualifiedName":"im_flutter_sdk.EMContactManager.deleteContact","href":"im_flutter_sdk/EMContactManager/deleteContact.html","type":"method","overriddenDepth":0,"enclosedBy":{"name":"EMContactManager","type":"class"}},{"name":"getAllContactsFromServer","qualifiedName":"im_flutter_sdk.EMContactManager.getAllContactsFromServer","href":"im_flutter_sdk/EMContactManager/getAllContactsFromServer.html","type":"method","overriddenDepth":0,"enclosedBy":{"name":"EMContactManager","type":"class"}},{"name":"getBlackListFromServer","qualifiedName":"im_flutter_sdk.EMContactManager.getBlackListFromServer","href":"im_flutter_sdk/EMContactManager/getBlackListFromServer.html","type":"method","overriddenDepth":0,"enclosedBy":{"name":"EMContactManager","type":"class"}},{"name":"getBlackListUserNames","qualifiedName":"im_flutter_sdk.EMContactManager.getBlackListUserNames","href":"im_flutter_sdk/EMContactManager/getBlackListUserNames.html","type":"method","overriddenDepth":0,"enclosedBy":{"name":"EMContactManager","type":"class"}},{"name":"hashCode","qualifiedName":"im_flutter_sdk.EMContactManager.hashCode","href":"im_flutter_sdk/EMContactManager/hashCode.html","type":"property","overriddenDepth":0,"enclosedBy":{"name":"EMContactManager","type":"class"}},{"name":"noSuchMethod","qualifiedName":"im_flutter_sdk.EMContactManager.noSuchMethod","href":"im_flutter_sdk/EMContactManager/noSuchMethod.html","type":"method","overriddenDepth":0,"enclosedBy":{"name":"EMContactManager","type":"class"}},{"name":"removeContactListener","qualifiedName":"im_flutter_sdk.EMContactManager.removeContactListener","href":"im_flutter_sdk/EMContactManager/removeContactListener.html","type":"method","overriddenDepth":0,"enclosedBy":{"name":"EMContactManager","type":"class"}},{"name":"removeUserFromBlackList","qualifiedName":"im_flutter_sdk.EMContactManager.removeUserFromBlackList","href":"im_flutter_sdk/EMContactManager/removeUserFromBlackList.html","type":"method","overriddenDepth":0,"enclosedBy":{"name":"EMContactManager","type":"class"}},{"name":"runtimeType","qualifiedName":"im_flutter_sdk.EMContactManager.runtimeType","href":"im_flutter_sdk/EMContactManager/runtimeType.html","type":"property","overriddenDepth":0,"enclosedBy":{"name":"EMContactManager","type":"class"}},{"name":"toString","qualifiedName":"im_flutter_sdk.EMContactManager.toString","href":"im_flutter_sdk/EMContactManager/toString.html","type":"method","overriddenDepth":0,"enclosedBy":{"name":"EMContactManager","type":"class"}},{"name":"EMConversation","qualifiedName":"im_flutter_sdk.EMConversation","href":"im_flutter_sdk/EMConversation-class.html","type":"class","overriddenDepth":0,"enclosedBy":{"name":"im_flutter_sdk","type":"library"}},{"name":"operator ==","qualifiedName":"im_flutter_sdk.EMConversation.==","href":"im_flutter_sdk/EMConversation/operator_equals.html","type":"method","overriddenDepth":0,"enclosedBy":{"name":"EMConversation","type":"class"}},{"name":"appendMessage","qualifiedName":"im_flutter_sdk.EMConversation.appendMessage","href":"im_flutter_sdk/EMConversation/appendMessage.html","type":"method","overriddenDepth":0,"enclosedBy":{"name":"EMConversation","type":"class"}},{"name":"clear","qualifiedName":"im_flutter_sdk.EMConversation.clear","href":"im_flutter_sdk/EMConversation/clear.html","type":"method","overriddenDepth":0,"enclosedBy":{"name":"EMConversation","type":"class"}},{"name":"clearAllMessages","qualifiedName":"im_flutter_sdk.EMConversation.clearAllMessages","href":"im_flutter_sdk/EMConversation/clearAllMessages.html","type":"method","overriddenDepth":0,"enclosedBy":{"name":"EMConversation","type":"class"}},{"name":"conversationId","qualifiedName":"im_flutter_sdk.EMConversation.conversationId","href":"im_flutter_sdk/EMConversation/conversationId.html","type":"property","overriddenDepth":0,"enclosedBy":{"name":"EMConversation","type":"class"}},{"name":"extField","qualifiedName":"im_flutter_sdk.EMConversation.extField","href":"im_flutter_sdk/EMConversation/extField.html","type":"property","overriddenDepth":0,"enclosedBy":{"name":"EMConversation","type":"class"}},{"name":"getLastMessage","qualifiedName":"im_flutter_sdk.EMConversation.getLastMessage","href":"im_flutter_sdk/EMConversation/getLastMessage.html","type":"method","overriddenDepth":0,"enclosedBy":{"name":"EMConversation","type":"class"}},{"name":"getLatestMessageFromOthers","qualifiedName":"im_flutter_sdk.EMConversation.getLatestMessageFromOthers","href":"im_flutter_sdk/EMConversation/getLatestMessageFromOthers.html","type":"method","overriddenDepth":0,"enclosedBy":{"name":"EMConversation","type":"class"}},{"name":"getMessage","qualifiedName":"im_flutter_sdk.EMConversation.getMessage","href":"im_flutter_sdk/EMConversation/getMessage.html","type":"method","overriddenDepth":0,"enclosedBy":{"name":"EMConversation","type":"class"}},{"name":"getUnreadMsgCount","qualifiedName":"im_flutter_sdk.EMConversation.getUnreadMsgCount","href":"im_flutter_sdk/EMConversation/getUnreadMsgCount.html","type":"method","overriddenDepth":0,"enclosedBy":{"name":"EMConversation","type":"class"}},{"name":"hashCode","qualifiedName":"im_flutter_sdk.EMConversation.hashCode","href":"im_flutter_sdk/EMConversation/hashCode.html","type":"property","overriddenDepth":0,"enclosedBy":{"name":"EMConversation","type":"class"}},{"name":"insertMessage","qualifiedName":"im_flutter_sdk.EMConversation.insertMessage","href":"im_flutter_sdk/EMConversation/insertMessage.html","type":"method","overriddenDepth":0,"enclosedBy":{"name":"EMConversation","type":"class"}},{"name":"isGroup","qualifiedName":"im_flutter_sdk.EMConversation.isGroup","href":"im_flutter_sdk/EMConversation/isGroup.html","type":"method","overriddenDepth":0,"enclosedBy":{"name":"EMConversation","type":"class"}},{"name":"loadMoreMsgFromDB","qualifiedName":"im_flutter_sdk.EMConversation.loadMoreMsgFromDB","href":"im_flutter_sdk/EMConversation/loadMoreMsgFromDB.html","type":"method","overriddenDepth":0,"enclosedBy":{"name":"EMConversation","type":"class"}},{"name":"markAllMessagesAsRead","qualifiedName":"im_flutter_sdk.EMConversation.markAllMessagesAsRead","href":"im_flutter_sdk/EMConversation/markAllMessagesAsRead.html","type":"method","overriddenDepth":0,"enclosedBy":{"name":"EMConversation","type":"class"}},{"name":"markMessageAsRead","qualifiedName":"im_flutter_sdk.EMConversation.markMessageAsRead","href":"im_flutter_sdk/EMConversation/markMessageAsRead.html","type":"method","overriddenDepth":0,"enclosedBy":{"name":"EMConversation","type":"class"}},{"name":"noSuchMethod","qualifiedName":"im_flutter_sdk.EMConversation.noSuchMethod","href":"im_flutter_sdk/EMConversation/noSuchMethod.html","type":"method","overriddenDepth":0,"enclosedBy":{"name":"EMConversation","type":"class"}},{"name":"removeMessage","qualifiedName":"im_flutter_sdk.EMConversation.removeMessage","href":"im_flutter_sdk/EMConversation/removeMessage.html","type":"method","overriddenDepth":0,"enclosedBy":{"name":"EMConversation","type":"class"}},{"name":"runtimeType","qualifiedName":"im_flutter_sdk.EMConversation.runtimeType","href":"im_flutter_sdk/EMConversation/runtimeType.html","type":"property","overriddenDepth":0,"enclosedBy":{"name":"EMConversation","type":"class"}},{"name":"searchMsgFromDB","qualifiedName":"im_flutter_sdk.EMConversation.searchMsgFromDB","href":"im_flutter_sdk/EMConversation/searchMsgFromDB.html","type":"method","overriddenDepth":0,"enclosedBy":{"name":"EMConversation","type":"class"}},{"name":"searchMsgFromDBByType","qualifiedName":"im_flutter_sdk.EMConversation.searchMsgFromDBByType","href":"im_flutter_sdk/EMConversation/searchMsgFromDBByType.html","type":"method","overriddenDepth":0,"enclosedBy":{"name":"EMConversation","type":"class"}},{"name":"toString","qualifiedName":"im_flutter_sdk.EMConversation.toString","href":"im_flutter_sdk/EMConversation/toString.html","type":"method","overriddenDepth":0,"enclosedBy":{"name":"EMConversation","type":"class"}},{"name":"type","qualifiedName":"im_flutter_sdk.EMConversation.type","href":"im_flutter_sdk/EMConversation/type.html","type":"property","overriddenDepth":0,"enclosedBy":{"name":"EMConversation","type":"class"}},{"name":"updateMessage","qualifiedName":"im_flutter_sdk.EMConversation.updateMessage","href":"im_flutter_sdk/EMConversation/updateMessage.html","type":"method","overriddenDepth":0,"enclosedBy":{"name":"EMConversation","type":"class"}},{"name":"EMDeviceInfo","qualifiedName":"im_flutter_sdk.EMDeviceInfo","href":"im_flutter_sdk/EMDeviceInfo-class.html","type":"class","overriddenDepth":0,"enclosedBy":{"name":"im_flutter_sdk","type":"library"}},{"name":"EMDeviceInfo","qualifiedName":"im_flutter_sdk.EMDeviceInfo","href":"im_flutter_sdk/EMDeviceInfo/EMDeviceInfo.html","type":"constructor","overriddenDepth":0,"enclosedBy":{"name":"EMDeviceInfo","type":"class"}},{"name":"operator ==","qualifiedName":"im_flutter_sdk.EMDeviceInfo.==","href":"im_flutter_sdk/EMDeviceInfo/operator_equals.html","type":"method","overriddenDepth":0,"enclosedBy":{"name":"EMDeviceInfo","type":"class"}},{"name":"deviceName","qualifiedName":"im_flutter_sdk.EMDeviceInfo.deviceName","href":"im_flutter_sdk/EMDeviceInfo/deviceName.html","type":"property","overriddenDepth":0,"enclosedBy":{"name":"EMDeviceInfo","type":"class"}},{"name":"deviceUUID","qualifiedName":"im_flutter_sdk.EMDeviceInfo.deviceUUID","href":"im_flutter_sdk/EMDeviceInfo/deviceUUID.html","type":"property","overriddenDepth":0,"enclosedBy":{"name":"EMDeviceInfo","type":"class"}},{"name":"hashCode","qualifiedName":"im_flutter_sdk.EMDeviceInfo.hashCode","href":"im_flutter_sdk/EMDeviceInfo/hashCode.html","type":"property","overriddenDepth":0,"enclosedBy":{"name":"EMDeviceInfo","type":"class"}},{"name":"noSuchMethod","qualifiedName":"im_flutter_sdk.EMDeviceInfo.noSuchMethod","href":"im_flutter_sdk/EMDeviceInfo/noSuchMethod.html","type":"method","overriddenDepth":0,"enclosedBy":{"name":"EMDeviceInfo","type":"class"}},{"name":"resource","qualifiedName":"im_flutter_sdk.EMDeviceInfo.resource","href":"im_flutter_sdk/EMDeviceInfo/resource.html","type":"property","overriddenDepth":0,"enclosedBy":{"name":"EMDeviceInfo","type":"class"}},{"name":"runtimeType","qualifiedName":"im_flutter_sdk.EMDeviceInfo.runtimeType","href":"im_flutter_sdk/EMDeviceInfo/runtimeType.html","type":"property","overriddenDepth":0,"enclosedBy":{"name":"EMDeviceInfo","type":"class"}},{"name":"toString","qualifiedName":"im_flutter_sdk.EMDeviceInfo.toString","href":"im_flutter_sdk/EMDeviceInfo/toString.html","type":"method","overriddenDepth":0,"enclosedBy":{"name":"EMDeviceInfo","type":"class"}},{"name":"EMFileMessageBody","qualifiedName":"im_flutter_sdk.EMFileMessageBody","href":"im_flutter_sdk/EMFileMessageBody-class.html","type":"class","overriddenDepth":0,"enclosedBy":{"name":"im_flutter_sdk","type":"library"}},{"name":"EMFileMessageBody","qualifiedName":"im_flutter_sdk.EMFileMessageBody","href":"im_flutter_sdk/EMFileMessageBody/EMFileMessageBody.html","type":"constructor","overriddenDepth":0,"enclosedBy":{"name":"EMFileMessageBody","type":"class"}},{"name":"operator ==","qualifiedName":"im_flutter_sdk.EMFileMessageBody.==","href":"im_flutter_sdk/EMFileMessageBody/operator_equals.html","type":"method","overriddenDepth":0,"enclosedBy":{"name":"EMFileMessageBody","type":"class"}},{"name":"displayName","qualifiedName":"im_flutter_sdk.EMFileMessageBody.displayName","href":"im_flutter_sdk/EMFileMessageBody/displayName.html","type":"property","overriddenDepth":0,"enclosedBy":{"name":"EMFileMessageBody","type":"class"}},{"name":"downloadStatus","qualifiedName":"im_flutter_sdk.EMFileMessageBody.downloadStatus","href":"im_flutter_sdk/EMFileMessageBody/downloadStatus.html","type":"property","overriddenDepth":0,"enclosedBy":{"name":"EMFileMessageBody","type":"class"}},{"name":"fileName","qualifiedName":"im_flutter_sdk.EMFileMessageBody.fileName","href":"im_flutter_sdk/EMFileMessageBody/fileName.html","type":"property","overriddenDepth":0,"enclosedBy":{"name":"EMFileMessageBody","type":"class"}},{"name":"hashCode","qualifiedName":"im_flutter_sdk.EMFileMessageBody.hashCode","href":"im_flutter_sdk/EMFileMessageBody/hashCode.html","type":"property","overriddenDepth":0,"enclosedBy":{"name":"EMFileMessageBody","type":"class"}},{"name":"localUrl","qualifiedName":"im_flutter_sdk.EMFileMessageBody.localUrl","href":"im_flutter_sdk/EMFileMessageBody/localUrl.html","type":"property","overriddenDepth":0,"enclosedBy":{"name":"EMFileMessageBody","type":"class"}},{"name":"noSuchMethod","qualifiedName":"im_flutter_sdk.EMFileMessageBody.noSuchMethod","href":"im_flutter_sdk/EMFileMessageBody/noSuchMethod.html","type":"method","overriddenDepth":0,"enclosedBy":{"name":"EMFileMessageBody","type":"class"}},{"name":"remoteUrl","qualifiedName":"im_flutter_sdk.EMFileMessageBody.remoteUrl","href":"im_flutter_sdk/EMFileMessageBody/remoteUrl.html","type":"property","overriddenDepth":0,"enclosedBy":{"name":"EMFileMessageBody","type":"class"}},{"name":"runtimeType","qualifiedName":"im_flutter_sdk.EMFileMessageBody.runtimeType","href":"im_flutter_sdk/EMFileMessageBody/runtimeType.html","type":"property","overriddenDepth":0,"enclosedBy":{"name":"EMFileMessageBody","type":"class"}},{"name":"EMGroup","qualifiedName":"im_flutter_sdk.EMGroup","href":"im_flutter_sdk/EMGroup-class.html","type":"class","overriddenDepth":0,"enclosedBy":{"name":"im_flutter_sdk","type":"library"}},{"name":"EMGroup","qualifiedName":"im_flutter_sdk.EMGroup","href":"im_flutter_sdk/EMGroup/EMGroup.html","type":"constructor","overriddenDepth":0,"enclosedBy":{"name":"EMGroup","type":"class"}},{"name":"operator ==","qualifiedName":"im_flutter_sdk.EMGroup.==","href":"im_flutter_sdk/EMGroup/operator_equals.html","type":"method","overriddenDepth":0,"enclosedBy":{"name":"EMGroup","type":"class"}},{"name":"getAdminList","qualifiedName":"im_flutter_sdk.EMGroup.getAdminList","href":"im_flutter_sdk/EMGroup/getAdminList.html","type":"method","overriddenDepth":0,"enclosedBy":{"name":"EMGroup","type":"class"}},{"name":"getAnnouncement","qualifiedName":"im_flutter_sdk.EMGroup.getAnnouncement","href":"im_flutter_sdk/EMGroup/getAnnouncement.html","type":"method","overriddenDepth":0,"enclosedBy":{"name":"EMGroup","type":"class"}},{"name":"getBlackList","qualifiedName":"im_flutter_sdk.EMGroup.getBlackList","href":"im_flutter_sdk/EMGroup/getBlackList.html","type":"method","overriddenDepth":0,"enclosedBy":{"name":"EMGroup","type":"class"}},{"name":"getDescription","qualifiedName":"im_flutter_sdk.EMGroup.getDescription","href":"im_flutter_sdk/EMGroup/getDescription.html","type":"method","overriddenDepth":0,"enclosedBy":{"name":"EMGroup","type":"class"}},{"name":"getExtension","qualifiedName":"im_flutter_sdk.EMGroup.getExtension","href":"im_flutter_sdk/EMGroup/getExtension.html","type":"method","overriddenDepth":0,"enclosedBy":{"name":"EMGroup","type":"class"}},{"name":"getGroupId","qualifiedName":"im_flutter_sdk.EMGroup.getGroupId","href":"im_flutter_sdk/EMGroup/getGroupId.html","type":"method","overriddenDepth":0,"enclosedBy":{"name":"EMGroup","type":"class"}},{"name":"getGroupName","qualifiedName":"im_flutter_sdk.EMGroup.getGroupName","href":"im_flutter_sdk/EMGroup/getGroupName.html","type":"method","overriddenDepth":0,"enclosedBy":{"name":"EMGroup","type":"class"}},{"name":"getMaxUserCount","qualifiedName":"im_flutter_sdk.EMGroup.getMaxUserCount","href":"im_flutter_sdk/EMGroup/getMaxUserCount.html","type":"method","overriddenDepth":0,"enclosedBy":{"name":"EMGroup","type":"class"}},{"name":"getMemberCount","qualifiedName":"im_flutter_sdk.EMGroup.getMemberCount","href":"im_flutter_sdk/EMGroup/getMemberCount.html","type":"method","overriddenDepth":0,"enclosedBy":{"name":"EMGroup","type":"class"}},{"name":"getMembers","qualifiedName":"im_flutter_sdk.EMGroup.getMembers","href":"im_flutter_sdk/EMGroup/getMembers.html","type":"method","overriddenDepth":0,"enclosedBy":{"name":"EMGroup","type":"class"}},{"name":"getMuteList","qualifiedName":"im_flutter_sdk.EMGroup.getMuteList","href":"im_flutter_sdk/EMGroup/getMuteList.html","type":"method","overriddenDepth":0,"enclosedBy":{"name":"EMGroup","type":"class"}},{"name":"getOccupants","qualifiedName":"im_flutter_sdk.EMGroup.getOccupants","href":"im_flutter_sdk/EMGroup/getOccupants.html","type":"method","overriddenDepth":0,"enclosedBy":{"name":"EMGroup","type":"class"}},{"name":"getOwner","qualifiedName":"im_flutter_sdk.EMGroup.getOwner","href":"im_flutter_sdk/EMGroup/getOwner.html","type":"method","overriddenDepth":0,"enclosedBy":{"name":"EMGroup","type":"class"}},{"name":"getPermissionType","qualifiedName":"im_flutter_sdk.EMGroup.getPermissionType","href":"im_flutter_sdk/EMGroup/getPermissionType.html","type":"method","overriddenDepth":0,"enclosedBy":{"name":"EMGroup","type":"class"}},{"name":"getSharedFileList","qualifiedName":"im_flutter_sdk.EMGroup.getSharedFileList","href":"im_flutter_sdk/EMGroup/getSharedFileList.html","type":"method","overriddenDepth":0,"enclosedBy":{"name":"EMGroup","type":"class"}},{"name":"hashCode","qualifiedName":"im_flutter_sdk.EMGroup.hashCode","href":"im_flutter_sdk/EMGroup/hashCode.html","type":"property","overriddenDepth":0,"enclosedBy":{"name":"EMGroup","type":"class"}},{"name":"isMemberAllowToInvite","qualifiedName":"im_flutter_sdk.EMGroup.isMemberAllowToInvite","href":"im_flutter_sdk/EMGroup/isMemberAllowToInvite.html","type":"method","overriddenDepth":0,"enclosedBy":{"name":"EMGroup","type":"class"}},{"name":"isMsgBlocked","qualifiedName":"im_flutter_sdk.EMGroup.isMsgBlocked","href":"im_flutter_sdk/EMGroup/isMsgBlocked.html","type":"method","overriddenDepth":0,"enclosedBy":{"name":"EMGroup","type":"class"}},{"name":"isPublic","qualifiedName":"im_flutter_sdk.EMGroup.isPublic","href":"im_flutter_sdk/EMGroup/isPublic.html","type":"method","overriddenDepth":0,"enclosedBy":{"name":"EMGroup","type":"class"}},{"name":"isPushNotificationEnabled","qualifiedName":"im_flutter_sdk.EMGroup.isPushNotificationEnabled","href":"im_flutter_sdk/EMGroup/isPushNotificationEnabled.html","type":"method","overriddenDepth":0,"enclosedBy":{"name":"EMGroup","type":"class"}},{"name":"noSuchMethod","qualifiedName":"im_flutter_sdk.EMGroup.noSuchMethod","href":"im_flutter_sdk/EMGroup/noSuchMethod.html","type":"method","overriddenDepth":0,"enclosedBy":{"name":"EMGroup","type":"class"}},{"name":"runtimeType","qualifiedName":"im_flutter_sdk.EMGroup.runtimeType","href":"im_flutter_sdk/EMGroup/runtimeType.html","type":"property","overriddenDepth":0,"enclosedBy":{"name":"EMGroup","type":"class"}},{"name":"EMGroupChangeListener","qualifiedName":"im_flutter_sdk.EMGroupChangeListener","href":"im_flutter_sdk/EMGroupChangeListener-class.html","type":"class","overriddenDepth":0,"enclosedBy":{"name":"im_flutter_sdk","type":"library"}},{"name":"EMGroupChangeListener","qualifiedName":"im_flutter_sdk.EMGroupChangeListener","href":"im_flutter_sdk/EMGroupChangeListener/EMGroupChangeListener.html","type":"constructor","overriddenDepth":0,"enclosedBy":{"name":"EMGroupChangeListener","type":"class"}},{"name":"operator ==","qualifiedName":"im_flutter_sdk.EMGroupChangeListener.==","href":"im_flutter_sdk/EMGroupChangeListener/operator_equals.html","type":"method","overriddenDepth":0,"enclosedBy":{"name":"EMGroupChangeListener","type":"class"}},{"name":"hashCode","qualifiedName":"im_flutter_sdk.EMGroupChangeListener.hashCode","href":"im_flutter_sdk/EMGroupChangeListener/hashCode.html","type":"property","overriddenDepth":0,"enclosedBy":{"name":"EMGroupChangeListener","type":"class"}},{"name":"noSuchMethod","qualifiedName":"im_flutter_sdk.EMGroupChangeListener.noSuchMethod","href":"im_flutter_sdk/EMGroupChangeListener/noSuchMethod.html","type":"method","overriddenDepth":0,"enclosedBy":{"name":"EMGroupChangeListener","type":"class"}},{"name":"onAdminAdded","qualifiedName":"im_flutter_sdk.EMGroupChangeListener.onAdminAdded","href":"im_flutter_sdk/EMGroupChangeListener/onAdminAdded.html","type":"method","overriddenDepth":0,"enclosedBy":{"name":"EMGroupChangeListener","type":"class"}},{"name":"onAdminRemoved","qualifiedName":"im_flutter_sdk.EMGroupChangeListener.onAdminRemoved","href":"im_flutter_sdk/EMGroupChangeListener/onAdminRemoved.html","type":"method","overriddenDepth":0,"enclosedBy":{"name":"EMGroupChangeListener","type":"class"}},{"name":"onAnnouncementChanged","qualifiedName":"im_flutter_sdk.EMGroupChangeListener.onAnnouncementChanged","href":"im_flutter_sdk/EMGroupChangeListener/onAnnouncementChanged.html","type":"method","overriddenDepth":0,"enclosedBy":{"name":"EMGroupChangeListener","type":"class"}},{"name":"onGroupDestroyed","qualifiedName":"im_flutter_sdk.EMGroupChangeListener.onGroupDestroyed","href":"im_flutter_sdk/EMGroupChangeListener/onGroupDestroyed.html","type":"method","overriddenDepth":0,"enclosedBy":{"name":"EMGroupChangeListener","type":"class"}},{"name":"onInvitationAccepted","qualifiedName":"im_flutter_sdk.EMGroupChangeListener.onInvitationAccepted","href":"im_flutter_sdk/EMGroupChangeListener/onInvitationAccepted.html","type":"method","overriddenDepth":0,"enclosedBy":{"name":"EMGroupChangeListener","type":"class"}},{"name":"onInvitationDeclined","qualifiedName":"im_flutter_sdk.EMGroupChangeListener.onInvitationDeclined","href":"im_flutter_sdk/EMGroupChangeListener/onInvitationDeclined.html","type":"method","overriddenDepth":0,"enclosedBy":{"name":"EMGroupChangeListener","type":"class"}},{"name":"onInvitationReceived","qualifiedName":"im_flutter_sdk.EMGroupChangeListener.onInvitationReceived","href":"im_flutter_sdk/EMGroupChangeListener/onInvitationReceived.html","type":"method","overriddenDepth":0,"enclosedBy":{"name":"EMGroupChangeListener","type":"class"}},{"name":"onMemberExited","qualifiedName":"im_flutter_sdk.EMGroupChangeListener.onMemberExited","href":"im_flutter_sdk/EMGroupChangeListener/onMemberExited.html","type":"method","overriddenDepth":0,"enclosedBy":{"name":"EMGroupChangeListener","type":"class"}},{"name":"onMemberJoined","qualifiedName":"im_flutter_sdk.EMGroupChangeListener.onMemberJoined","href":"im_flutter_sdk/EMGroupChangeListener/onMemberJoined.html","type":"method","overriddenDepth":0,"enclosedBy":{"name":"EMGroupChangeListener","type":"class"}},{"name":"onMuteListAdded","qualifiedName":"im_flutter_sdk.EMGroupChangeListener.onMuteListAdded","href":"im_flutter_sdk/EMGroupChangeListener/onMuteListAdded.html","type":"method","overriddenDepth":0,"enclosedBy":{"name":"EMGroupChangeListener","type":"class"}},{"name":"onMuteListRemoved","qualifiedName":"im_flutter_sdk.EMGroupChangeListener.onMuteListRemoved","href":"im_flutter_sdk/EMGroupChangeListener/onMuteListRemoved.html","type":"method","overriddenDepth":0,"enclosedBy":{"name":"EMGroupChangeListener","type":"class"}},{"name":"onOwnerChanged","qualifiedName":"im_flutter_sdk.EMGroupChangeListener.onOwnerChanged","href":"im_flutter_sdk/EMGroupChangeListener/onOwnerChanged.html","type":"method","overriddenDepth":0,"enclosedBy":{"name":"EMGroupChangeListener","type":"class"}},{"name":"onRequestToJoinAccepted","qualifiedName":"im_flutter_sdk.EMGroupChangeListener.onRequestToJoinAccepted","href":"im_flutter_sdk/EMGroupChangeListener/onRequestToJoinAccepted.html","type":"method","overriddenDepth":0,"enclosedBy":{"name":"EMGroupChangeListener","type":"class"}},{"name":"onRequestToJoinDeclined","qualifiedName":"im_flutter_sdk.EMGroupChangeListener.onRequestToJoinDeclined","href":"im_flutter_sdk/EMGroupChangeListener/onRequestToJoinDeclined.html","type":"method","overriddenDepth":0,"enclosedBy":{"name":"EMGroupChangeListener","type":"class"}},{"name":"onRequestToJoinReceived","qualifiedName":"im_flutter_sdk.EMGroupChangeListener.onRequestToJoinReceived","href":"im_flutter_sdk/EMGroupChangeListener/onRequestToJoinReceived.html","type":"method","overriddenDepth":0,"enclosedBy":{"name":"EMGroupChangeListener","type":"class"}},{"name":"onSharedFileAdded","qualifiedName":"im_flutter_sdk.EMGroupChangeListener.onSharedFileAdded","href":"im_flutter_sdk/EMGroupChangeListener/onSharedFileAdded.html","type":"method","overriddenDepth":0,"enclosedBy":{"name":"EMGroupChangeListener","type":"class"}},{"name":"onSharedFileDeleted","qualifiedName":"im_flutter_sdk.EMGroupChangeListener.onSharedFileDeleted","href":"im_flutter_sdk/EMGroupChangeListener/onSharedFileDeleted.html","type":"method","overriddenDepth":0,"enclosedBy":{"name":"EMGroupChangeListener","type":"class"}},{"name":"onUserRemoved","qualifiedName":"im_flutter_sdk.EMGroupChangeListener.onUserRemoved","href":"im_flutter_sdk/EMGroupChangeListener/onUserRemoved.html","type":"method","overriddenDepth":0,"enclosedBy":{"name":"EMGroupChangeListener","type":"class"}},{"name":"runtimeType","qualifiedName":"im_flutter_sdk.EMGroupChangeListener.runtimeType","href":"im_flutter_sdk/EMGroupChangeListener/runtimeType.html","type":"property","overriddenDepth":0,"enclosedBy":{"name":"EMGroupChangeListener","type":"class"}},{"name":"toString","qualifiedName":"im_flutter_sdk.EMGroupChangeListener.toString","href":"im_flutter_sdk/EMGroupChangeListener/toString.html","type":"method","overriddenDepth":0,"enclosedBy":{"name":"EMGroupChangeListener","type":"class"}},{"name":"EMGroupInfo","qualifiedName":"im_flutter_sdk.EMGroupInfo","href":"im_flutter_sdk/EMGroupInfo-class.html","type":"class","overriddenDepth":0,"enclosedBy":{"name":"im_flutter_sdk","type":"library"}},{"name":"operator ==","qualifiedName":"im_flutter_sdk.EMGroupInfo.==","href":"im_flutter_sdk/EMGroupInfo/operator_equals.html","type":"method","overriddenDepth":0,"enclosedBy":{"name":"EMGroupInfo","type":"class"}},{"name":"getGroupId","qualifiedName":"im_flutter_sdk.EMGroupInfo.getGroupId","href":"im_flutter_sdk/EMGroupInfo/getGroupId.html","type":"method","overriddenDepth":0,"enclosedBy":{"name":"EMGroupInfo","type":"class"}},{"name":"getGroupName","qualifiedName":"im_flutter_sdk.EMGroupInfo.getGroupName","href":"im_flutter_sdk/EMGroupInfo/getGroupName.html","type":"method","overriddenDepth":0,"enclosedBy":{"name":"EMGroupInfo","type":"class"}},{"name":"hashCode","qualifiedName":"im_flutter_sdk.EMGroupInfo.hashCode","href":"im_flutter_sdk/EMGroupInfo/hashCode.html","type":"property","overriddenDepth":0,"enclosedBy":{"name":"EMGroupInfo","type":"class"}},{"name":"noSuchMethod","qualifiedName":"im_flutter_sdk.EMGroupInfo.noSuchMethod","href":"im_flutter_sdk/EMGroupInfo/noSuchMethod.html","type":"method","overriddenDepth":0,"enclosedBy":{"name":"EMGroupInfo","type":"class"}},{"name":"runtimeType","qualifiedName":"im_flutter_sdk.EMGroupInfo.runtimeType","href":"im_flutter_sdk/EMGroupInfo/runtimeType.html","type":"property","overriddenDepth":0,"enclosedBy":{"name":"EMGroupInfo","type":"class"}},{"name":"toString","qualifiedName":"im_flutter_sdk.EMGroupInfo.toString","href":"im_flutter_sdk/EMGroupInfo/toString.html","type":"method","overriddenDepth":0,"enclosedBy":{"name":"EMGroupInfo","type":"class"}},{"name":"EMGroupManager","qualifiedName":"im_flutter_sdk.EMGroupManager","href":"im_flutter_sdk/EMGroupManager-class.html","type":"class","overriddenDepth":0,"enclosedBy":{"name":"im_flutter_sdk","type":"library"}},{"name":"operator ==","qualifiedName":"im_flutter_sdk.EMGroupManager.==","href":"im_flutter_sdk/EMGroupManager/operator_equals.html","type":"method","overriddenDepth":0,"enclosedBy":{"name":"EMGroupManager","type":"class"}},{"name":"acceptApplication","qualifiedName":"im_flutter_sdk.EMGroupManager.acceptApplication","href":"im_flutter_sdk/EMGroupManager/acceptApplication.html","type":"method","overriddenDepth":0,"enclosedBy":{"name":"EMGroupManager","type":"class"}},{"name":"acceptInvitation","qualifiedName":"im_flutter_sdk.EMGroupManager.acceptInvitation","href":"im_flutter_sdk/EMGroupManager/acceptInvitation.html","type":"method","overriddenDepth":0,"enclosedBy":{"name":"EMGroupManager","type":"class"}},{"name":"addGroupAdmin","qualifiedName":"im_flutter_sdk.EMGroupManager.addGroupAdmin","href":"im_flutter_sdk/EMGroupManager/addGroupAdmin.html","type":"method","overriddenDepth":0,"enclosedBy":{"name":"EMGroupManager","type":"class"}},{"name":"addUsersToGroup","qualifiedName":"im_flutter_sdk.EMGroupManager.addUsersToGroup","href":"im_flutter_sdk/EMGroupManager/addUsersToGroup.html","type":"method","overriddenDepth":0,"enclosedBy":{"name":"EMGroupManager","type":"class"}},{"name":"applyJoinToGroup","qualifiedName":"im_flutter_sdk.EMGroupManager.applyJoinToGroup","href":"im_flutter_sdk/EMGroupManager/applyJoinToGroup.html","type":"method","overriddenDepth":0,"enclosedBy":{"name":"EMGroupManager","type":"class"}},{"name":"blockGroupMessage","qualifiedName":"im_flutter_sdk.EMGroupManager.blockGroupMessage","href":"im_flutter_sdk/EMGroupManager/blockGroupMessage.html","type":"method","overriddenDepth":0,"enclosedBy":{"name":"EMGroupManager","type":"class"}},{"name":"blockUser","qualifiedName":"im_flutter_sdk.EMGroupManager.blockUser","href":"im_flutter_sdk/EMGroupManager/blockUser.html","type":"method","overriddenDepth":0,"enclosedBy":{"name":"EMGroupManager","type":"class"}},{"name":"changeGroupDescription","qualifiedName":"im_flutter_sdk.EMGroupManager.changeGroupDescription","href":"im_flutter_sdk/EMGroupManager/changeGroupDescription.html","type":"method","overriddenDepth":0,"enclosedBy":{"name":"EMGroupManager","type":"class"}},{"name":"changeGroupName","qualifiedName":"im_flutter_sdk.EMGroupManager.changeGroupName","href":"im_flutter_sdk/EMGroupManager/changeGroupName.html","type":"method","overriddenDepth":0,"enclosedBy":{"name":"EMGroupManager","type":"class"}},{"name":"changeOwner","qualifiedName":"im_flutter_sdk.EMGroupManager.changeOwner","href":"im_flutter_sdk/EMGroupManager/changeOwner.html","type":"method","overriddenDepth":0,"enclosedBy":{"name":"EMGroupManager","type":"class"}},{"name":"createGroup","qualifiedName":"im_flutter_sdk.EMGroupManager.createGroup","href":"im_flutter_sdk/EMGroupManager/createGroup.html","type":"method","overriddenDepth":0,"enclosedBy":{"name":"EMGroupManager","type":"class"}},{"name":"declineApplication","qualifiedName":"im_flutter_sdk.EMGroupManager.declineApplication","href":"im_flutter_sdk/EMGroupManager/declineApplication.html","type":"method","overriddenDepth":0,"enclosedBy":{"name":"EMGroupManager","type":"class"}},{"name":"declineInvitation","qualifiedName":"im_flutter_sdk.EMGroupManager.declineInvitation","href":"im_flutter_sdk/EMGroupManager/declineInvitation.html","type":"method","overriddenDepth":0,"enclosedBy":{"name":"EMGroupManager","type":"class"}},{"name":"deleteGroupSharedFile","qualifiedName":"im_flutter_sdk.EMGroupManager.deleteGroupSharedFile","href":"im_flutter_sdk/EMGroupManager/deleteGroupSharedFile.html","type":"method","overriddenDepth":0,"enclosedBy":{"name":"EMGroupManager","type":"class"}},{"name":"destroyGroup","qualifiedName":"im_flutter_sdk.EMGroupManager.destroyGroup","href":"im_flutter_sdk/EMGroupManager/destroyGroup.html","type":"method","overriddenDepth":0,"enclosedBy":{"name":"EMGroupManager","type":"class"}},{"name":"downloadGroupSharedFile","qualifiedName":"im_flutter_sdk.EMGroupManager.downloadGroupSharedFile","href":"im_flutter_sdk/EMGroupManager/downloadGroupSharedFile.html","type":"method","overriddenDepth":0,"enclosedBy":{"name":"EMGroupManager","type":"class"}},{"name":"fetchGroupAnnouncement","qualifiedName":"im_flutter_sdk.EMGroupManager.fetchGroupAnnouncement","href":"im_flutter_sdk/EMGroupManager/fetchGroupAnnouncement.html","type":"method","overriddenDepth":0,"enclosedBy":{"name":"EMGroupManager","type":"class"}},{"name":"fetchGroupBlackList","qualifiedName":"im_flutter_sdk.EMGroupManager.fetchGroupBlackList","href":"im_flutter_sdk/EMGroupManager/fetchGroupBlackList.html","type":"method","overriddenDepth":0,"enclosedBy":{"name":"EMGroupManager","type":"class"}},{"name":"fetchGroupMembers","qualifiedName":"im_flutter_sdk.EMGroupManager.fetchGroupMembers","href":"im_flutter_sdk/EMGroupManager/fetchGroupMembers.html","type":"method","overriddenDepth":0,"enclosedBy":{"name":"EMGroupManager","type":"class"}},{"name":"fetchGroupMuteList","qualifiedName":"im_flutter_sdk.EMGroupManager.fetchGroupMuteList","href":"im_flutter_sdk/EMGroupManager/fetchGroupMuteList.html","type":"method","overriddenDepth":0,"enclosedBy":{"name":"EMGroupManager","type":"class"}},{"name":"fetchGroupSharedFileList","qualifiedName":"im_flutter_sdk.EMGroupManager.fetchGroupSharedFileList","href":"im_flutter_sdk/EMGroupManager/fetchGroupSharedFileList.html","type":"method","overriddenDepth":0,"enclosedBy":{"name":"EMGroupManager","type":"class"}},{"name":"getAllGroups","qualifiedName":"im_flutter_sdk.EMGroupManager.getAllGroups","href":"im_flutter_sdk/EMGroupManager/getAllGroups.html","type":"method","overriddenDepth":0,"enclosedBy":{"name":"EMGroupManager","type":"class"}},{"name":"getGroup","qualifiedName":"im_flutter_sdk.EMGroupManager.getGroup","href":"im_flutter_sdk/EMGroupManager/getGroup.html","type":"method","overriddenDepth":0,"enclosedBy":{"name":"EMGroupManager","type":"class"}},{"name":"getGroupFromServer","qualifiedName":"im_flutter_sdk.EMGroupManager.getGroupFromServer","href":"im_flutter_sdk/EMGroupManager/getGroupFromServer.html","type":"method","overriddenDepth":0,"enclosedBy":{"name":"EMGroupManager","type":"class"}},{"name":"getJoinedGroupsFromServer","qualifiedName":"im_flutter_sdk.EMGroupManager.getJoinedGroupsFromServer","href":"im_flutter_sdk/EMGroupManager/getJoinedGroupsFromServer.html","type":"method","overriddenDepth":0,"enclosedBy":{"name":"EMGroupManager","type":"class"}},{"name":"getPublicGroupsFromServer","qualifiedName":"im_flutter_sdk.EMGroupManager.getPublicGroupsFromServer","href":"im_flutter_sdk/EMGroupManager/getPublicGroupsFromServer.html","type":"method","overriddenDepth":0,"enclosedBy":{"name":"EMGroupManager","type":"class"}},{"name":"hashCode","qualifiedName":"im_flutter_sdk.EMGroupManager.hashCode","href":"im_flutter_sdk/EMGroupManager/hashCode.html","type":"property","overriddenDepth":0,"enclosedBy":{"name":"EMGroupManager","type":"class"}},{"name":"inviteUser","qualifiedName":"im_flutter_sdk.EMGroupManager.inviteUser","href":"im_flutter_sdk/EMGroupManager/inviteUser.html","type":"method","overriddenDepth":0,"enclosedBy":{"name":"EMGroupManager","type":"class"}},{"name":"joinGroup","qualifiedName":"im_flutter_sdk.EMGroupManager.joinGroup","href":"im_flutter_sdk/EMGroupManager/joinGroup.html","type":"method","overriddenDepth":0,"enclosedBy":{"name":"EMGroupManager","type":"class"}},{"name":"leaveGroup","qualifiedName":"im_flutter_sdk.EMGroupManager.leaveGroup","href":"im_flutter_sdk/EMGroupManager/leaveGroup.html","type":"method","overriddenDepth":0,"enclosedBy":{"name":"EMGroupManager","type":"class"}},{"name":"loadAllGroups","qualifiedName":"im_flutter_sdk.EMGroupManager.loadAllGroups","href":"im_flutter_sdk/EMGroupManager/loadAllGroups.html","type":"method","overriddenDepth":0,"enclosedBy":{"name":"EMGroupManager","type":"class"}},{"name":"muteGroupMembers","qualifiedName":"im_flutter_sdk.EMGroupManager.muteGroupMembers","href":"im_flutter_sdk/EMGroupManager/muteGroupMembers.html","type":"method","overriddenDepth":0,"enclosedBy":{"name":"EMGroupManager","type":"class"}},{"name":"noSuchMethod","qualifiedName":"im_flutter_sdk.EMGroupManager.noSuchMethod","href":"im_flutter_sdk/EMGroupManager/noSuchMethod.html","type":"method","overriddenDepth":0,"enclosedBy":{"name":"EMGroupManager","type":"class"}},{"name":"removeGroupAdmin","qualifiedName":"im_flutter_sdk.EMGroupManager.removeGroupAdmin","href":"im_flutter_sdk/EMGroupManager/removeGroupAdmin.html","type":"method","overriddenDepth":0,"enclosedBy":{"name":"EMGroupManager","type":"class"}},{"name":"removeUserFromGroup","qualifiedName":"im_flutter_sdk.EMGroupManager.removeUserFromGroup","href":"im_flutter_sdk/EMGroupManager/removeUserFromGroup.html","type":"method","overriddenDepth":0,"enclosedBy":{"name":"EMGroupManager","type":"class"}},{"name":"runtimeType","qualifiedName":"im_flutter_sdk.EMGroupManager.runtimeType","href":"im_flutter_sdk/EMGroupManager/runtimeType.html","type":"property","overriddenDepth":0,"enclosedBy":{"name":"EMGroupManager","type":"class"}},{"name":"toString","qualifiedName":"im_flutter_sdk.EMGroupManager.toString","href":"im_flutter_sdk/EMGroupManager/toString.html","type":"method","overriddenDepth":0,"enclosedBy":{"name":"EMGroupManager","type":"class"}},{"name":"unMuteGroupMembers","qualifiedName":"im_flutter_sdk.EMGroupManager.unMuteGroupMembers","href":"im_flutter_sdk/EMGroupManager/unMuteGroupMembers.html","type":"method","overriddenDepth":0,"enclosedBy":{"name":"EMGroupManager","type":"class"}},{"name":"unblockGroupMessage","qualifiedName":"im_flutter_sdk.EMGroupManager.unblockGroupMessage","href":"im_flutter_sdk/EMGroupManager/unblockGroupMessage.html","type":"method","overriddenDepth":0,"enclosedBy":{"name":"EMGroupManager","type":"class"}},{"name":"unblockUser","qualifiedName":"im_flutter_sdk.EMGroupManager.unblockUser","href":"im_flutter_sdk/EMGroupManager/unblockUser.html","type":"method","overriddenDepth":0,"enclosedBy":{"name":"EMGroupManager","type":"class"}},{"name":"updateGroupAnnouncement","qualifiedName":"im_flutter_sdk.EMGroupManager.updateGroupAnnouncement","href":"im_flutter_sdk/EMGroupManager/updateGroupAnnouncement.html","type":"method","overriddenDepth":0,"enclosedBy":{"name":"EMGroupManager","type":"class"}},{"name":"updateGroupExtension","qualifiedName":"im_flutter_sdk.EMGroupManager.updateGroupExtension","href":"im_flutter_sdk/EMGroupManager/updateGroupExtension.html","type":"method","overriddenDepth":0,"enclosedBy":{"name":"EMGroupManager","type":"class"}},{"name":"uploadGroupSharedFile","qualifiedName":"im_flutter_sdk.EMGroupManager.uploadGroupSharedFile","href":"im_flutter_sdk/EMGroupManager/uploadGroupSharedFile.html","type":"method","overriddenDepth":0,"enclosedBy":{"name":"EMGroupManager","type":"class"}},{"name":"EMGroupOptions","qualifiedName":"im_flutter_sdk.EMGroupOptions","href":"im_flutter_sdk/EMGroupOptions-class.html","type":"class","overriddenDepth":0,"enclosedBy":{"name":"im_flutter_sdk","type":"library"}},{"name":"EMGroupOptions","qualifiedName":"im_flutter_sdk.EMGroupOptions","href":"im_flutter_sdk/EMGroupOptions/EMGroupOptions.html","type":"constructor","overriddenDepth":0,"enclosedBy":{"name":"EMGroupOptions","type":"class"}},{"name":"operator ==","qualifiedName":"im_flutter_sdk.EMGroupOptions.==","href":"im_flutter_sdk/EMGroupOptions/operator_equals.html","type":"method","overriddenDepth":0,"enclosedBy":{"name":"EMGroupOptions","type":"class"}},{"name":"hashCode","qualifiedName":"im_flutter_sdk.EMGroupOptions.hashCode","href":"im_flutter_sdk/EMGroupOptions/hashCode.html","type":"property","overriddenDepth":0,"enclosedBy":{"name":"EMGroupOptions","type":"class"}},{"name":"maxUsers","qualifiedName":"im_flutter_sdk.EMGroupOptions.maxUsers","href":"im_flutter_sdk/EMGroupOptions/maxUsers.html","type":"property","overriddenDepth":0,"enclosedBy":{"name":"EMGroupOptions","type":"class"}},{"name":"noSuchMethod","qualifiedName":"im_flutter_sdk.EMGroupOptions.noSuchMethod","href":"im_flutter_sdk/EMGroupOptions/noSuchMethod.html","type":"method","overriddenDepth":0,"enclosedBy":{"name":"EMGroupOptions","type":"class"}},{"name":"runtimeType","qualifiedName":"im_flutter_sdk.EMGroupOptions.runtimeType","href":"im_flutter_sdk/EMGroupOptions/runtimeType.html","type":"property","overriddenDepth":0,"enclosedBy":{"name":"EMGroupOptions","type":"class"}},{"name":"style","qualifiedName":"im_flutter_sdk.EMGroupOptions.style","href":"im_flutter_sdk/EMGroupOptions/style.html","type":"property","overriddenDepth":0,"enclosedBy":{"name":"EMGroupOptions","type":"class"}},{"name":"toString","qualifiedName":"im_flutter_sdk.EMGroupOptions.toString","href":"im_flutter_sdk/EMGroupOptions/toString.html","type":"method","overriddenDepth":0,"enclosedBy":{"name":"EMGroupOptions","type":"class"}},{"name":"EMGroupPermissionType","qualifiedName":"im_flutter_sdk.EMGroupPermissionType","href":"im_flutter_sdk/EMGroupPermissionType-class.html","type":"enum","overriddenDepth":0,"enclosedBy":{"name":"im_flutter_sdk","type":"library"}},{"name":"operator ==","qualifiedName":"im_flutter_sdk.EMGroupPermissionType.==","href":"im_flutter_sdk/EMGroupPermissionType/operator_equals.html","type":"method","overriddenDepth":0,"enclosedBy":{"name":"EMGroupPermissionType","type":"enum"}},{"name":"hashCode","qualifiedName":"im_flutter_sdk.EMGroupPermissionType.hashCode","href":"im_flutter_sdk/EMGroupPermissionType/hashCode.html","type":"property","overriddenDepth":0,"enclosedBy":{"name":"EMGroupPermissionType","type":"enum"}},{"name":"noSuchMethod","qualifiedName":"im_flutter_sdk.EMGroupPermissionType.noSuchMethod","href":"im_flutter_sdk/EMGroupPermissionType/noSuchMethod.html","type":"method","overriddenDepth":0,"enclosedBy":{"name":"EMGroupPermissionType","type":"enum"}},{"name":"runtimeType","qualifiedName":"im_flutter_sdk.EMGroupPermissionType.runtimeType","href":"im_flutter_sdk/EMGroupPermissionType/runtimeType.html","type":"property","overriddenDepth":0,"enclosedBy":{"name":"EMGroupPermissionType","type":"enum"}},{"name":"toString","qualifiedName":"im_flutter_sdk.EMGroupPermissionType.toString","href":"im_flutter_sdk/EMGroupPermissionType/toString.html","type":"method","overriddenDepth":1,"enclosedBy":{"name":"EMGroupPermissionType","type":"enum"}},{"name":"EMGroupStyle","qualifiedName":"im_flutter_sdk.EMGroupStyle","href":"im_flutter_sdk/EMGroupStyle-class.html","type":"enum","overriddenDepth":0,"enclosedBy":{"name":"im_flutter_sdk","type":"library"}},{"name":"operator ==","qualifiedName":"im_flutter_sdk.EMGroupStyle.==","href":"im_flutter_sdk/EMGroupStyle/operator_equals.html","type":"method","overriddenDepth":0,"enclosedBy":{"name":"EMGroupStyle","type":"enum"}},{"name":"hashCode","qualifiedName":"im_flutter_sdk.EMGroupStyle.hashCode","href":"im_flutter_sdk/EMGroupStyle/hashCode.html","type":"property","overriddenDepth":0,"enclosedBy":{"name":"EMGroupStyle","type":"enum"}},{"name":"noSuchMethod","qualifiedName":"im_flutter_sdk.EMGroupStyle.noSuchMethod","href":"im_flutter_sdk/EMGroupStyle/noSuchMethod.html","type":"method","overriddenDepth":0,"enclosedBy":{"name":"EMGroupStyle","type":"enum"}},{"name":"runtimeType","qualifiedName":"im_flutter_sdk.EMGroupStyle.runtimeType","href":"im_flutter_sdk/EMGroupStyle/runtimeType.html","type":"property","overriddenDepth":0,"enclosedBy":{"name":"EMGroupStyle","type":"enum"}},{"name":"toString","qualifiedName":"im_flutter_sdk.EMGroupStyle.toString","href":"im_flutter_sdk/EMGroupStyle/toString.html","type":"method","overriddenDepth":1,"enclosedBy":{"name":"EMGroupStyle","type":"enum"}},{"name":"EMImageMessageBody","qualifiedName":"im_flutter_sdk.EMImageMessageBody","href":"im_flutter_sdk/EMImageMessageBody-class.html","type":"class","overriddenDepth":0,"enclosedBy":{"name":"im_flutter_sdk","type":"library"}},{"name":"EMImageMessageBody","qualifiedName":"im_flutter_sdk.EMImageMessageBody","href":"im_flutter_sdk/EMImageMessageBody/EMImageMessageBody.html","type":"constructor","overriddenDepth":0,"enclosedBy":{"name":"EMImageMessageBody","type":"class"}},{"name":"fileName","qualifiedName":"im_flutter_sdk.EMImageMessageBody.fileName","href":"im_flutter_sdk/EMImageMessageBody/fileName.html","type":"property","overriddenDepth":0,"enclosedBy":{"name":"EMImageMessageBody","type":"class"}},{"name":"height","qualifiedName":"im_flutter_sdk.EMImageMessageBody.height","href":"im_flutter_sdk/EMImageMessageBody/height.html","type":"property","overriddenDepth":0,"enclosedBy":{"name":"EMImageMessageBody","type":"class"}},{"name":"thumbnailLocalPath","qualifiedName":"im_flutter_sdk.EMImageMessageBody.thumbnailLocalPath","href":"im_flutter_sdk/EMImageMessageBody/thumbnailLocalPath.html","type":"property","overriddenDepth":0,"enclosedBy":{"name":"EMImageMessageBody","type":"class"}},{"name":"thumbnailUrl","qualifiedName":"im_flutter_sdk.EMImageMessageBody.thumbnailUrl","href":"im_flutter_sdk/EMImageMessageBody/thumbnailUrl.html","type":"property","overriddenDepth":0,"enclosedBy":{"name":"EMImageMessageBody","type":"class"}},{"name":"width","qualifiedName":"im_flutter_sdk.EMImageMessageBody.width","href":"im_flutter_sdk/EMImageMessageBody/width.html","type":"property","overriddenDepth":0,"enclosedBy":{"name":"EMImageMessageBody","type":"class"}},{"name":"EMLocationMessageBody","qualifiedName":"im_flutter_sdk.EMLocationMessageBody","href":"im_flutter_sdk/EMLocationMessageBody-class.html","type":"class","overriddenDepth":0,"enclosedBy":{"name":"im_flutter_sdk","type":"library"}},{"name":"EMLocationMessageBody","qualifiedName":"im_flutter_sdk.EMLocationMessageBody","href":"im_flutter_sdk/EMLocationMessageBody/EMLocationMessageBody.html","type":"constructor","overriddenDepth":0,"enclosedBy":{"name":"EMLocationMessageBody","type":"class"}},{"name":"operator ==","qualifiedName":"im_flutter_sdk.EMLocationMessageBody.==","href":"im_flutter_sdk/EMLocationMessageBody/operator_equals.html","type":"method","overriddenDepth":0,"enclosedBy":{"name":"EMLocationMessageBody","type":"class"}},{"name":"address","qualifiedName":"im_flutter_sdk.EMLocationMessageBody.address","href":"im_flutter_sdk/EMLocationMessageBody/address.html","type":"property","overriddenDepth":0,"enclosedBy":{"name":"EMLocationMessageBody","type":"class"}},{"name":"hashCode","qualifiedName":"im_flutter_sdk.EMLocationMessageBody.hashCode","href":"im_flutter_sdk/EMLocationMessageBody/hashCode.html","type":"property","overriddenDepth":0,"enclosedBy":{"name":"EMLocationMessageBody","type":"class"}},{"name":"latitude","qualifiedName":"im_flutter_sdk.EMLocationMessageBody.latitude","href":"im_flutter_sdk/EMLocationMessageBody/latitude.html","type":"property","overriddenDepth":0,"enclosedBy":{"name":"EMLocationMessageBody","type":"class"}},{"name":"longitude","qualifiedName":"im_flutter_sdk.EMLocationMessageBody.longitude","href":"im_flutter_sdk/EMLocationMessageBody/longitude.html","type":"property","overriddenDepth":0,"enclosedBy":{"name":"EMLocationMessageBody","type":"class"}},{"name":"noSuchMethod","qualifiedName":"im_flutter_sdk.EMLocationMessageBody.noSuchMethod","href":"im_flutter_sdk/EMLocationMessageBody/noSuchMethod.html","type":"method","overriddenDepth":0,"enclosedBy":{"name":"EMLocationMessageBody","type":"class"}},{"name":"runtimeType","qualifiedName":"im_flutter_sdk.EMLocationMessageBody.runtimeType","href":"im_flutter_sdk/EMLocationMessageBody/runtimeType.html","type":"property","overriddenDepth":0,"enclosedBy":{"name":"EMLocationMessageBody","type":"class"}},{"name":"EMMessage","qualifiedName":"im_flutter_sdk.EMMessage","href":"im_flutter_sdk/EMMessage-class.html","type":"class","overriddenDepth":0,"enclosedBy":{"name":"im_flutter_sdk","type":"library"}},{"name":"EMMessage","qualifiedName":"im_flutter_sdk.EMMessage","href":"im_flutter_sdk/EMMessage/EMMessage.html","type":"constructor","overriddenDepth":0,"enclosedBy":{"name":"EMMessage","type":"class"}},{"name":"operator ==","qualifiedName":"im_flutter_sdk.EMMessage.==","href":"im_flutter_sdk/EMMessage/operator_equals.html","type":"method","overriddenDepth":0,"enclosedBy":{"name":"EMMessage","type":"class"}},{"name":"acked","qualifiedName":"im_flutter_sdk.EMMessage.acked","href":"im_flutter_sdk/EMMessage/acked.html","type":"property","overriddenDepth":0,"enclosedBy":{"name":"EMMessage","type":"class"}},{"name":"body","qualifiedName":"im_flutter_sdk.EMMessage.body","href":"im_flutter_sdk/EMMessage/body.html","type":"property","overriddenDepth":0,"enclosedBy":{"name":"EMMessage","type":"class"}},{"name":"chatType","qualifiedName":"im_flutter_sdk.EMMessage.chatType","href":"im_flutter_sdk/EMMessage/chatType.html","type":"property","overriddenDepth":0,"enclosedBy":{"name":"EMMessage","type":"class"}},{"name":"conversationId","qualifiedName":"im_flutter_sdk.EMMessage.conversationId","href":"im_flutter_sdk/EMMessage/conversationId.html","type":"property","overriddenDepth":0,"enclosedBy":{"name":"EMMessage","type":"class"}},{"name":"EMMessage.createFileSendMessage","qualifiedName":"im_flutter_sdk.EMMessage.createFileSendMessage","href":"im_flutter_sdk/EMMessage/EMMessage.createFileSendMessage.html","type":"constructor","overriddenDepth":0,"enclosedBy":{"name":"EMMessage","type":"class"}},{"name":"EMMessage.createImageSendMessage","qualifiedName":"im_flutter_sdk.EMMessage.createImageSendMessage","href":"im_flutter_sdk/EMMessage/EMMessage.createImageSendMessage.html","type":"constructor","overriddenDepth":0,"enclosedBy":{"name":"EMMessage","type":"class"}},{"name":"EMMessage.createLocationSendMessage","qualifiedName":"im_flutter_sdk.EMMessage.createLocationSendMessage","href":"im_flutter_sdk/EMMessage/EMMessage.createLocationSendMessage.html","type":"constructor","overriddenDepth":0,"enclosedBy":{"name":"EMMessage","type":"class"}},{"name":"EMMessage.createReceiveMessage","qualifiedName":"im_flutter_sdk.EMMessage.createReceiveMessage","href":"im_flutter_sdk/EMMessage/EMMessage.createReceiveMessage.html","type":"constructor","overriddenDepth":0,"enclosedBy":{"name":"EMMessage","type":"class"}},{"name":"EMMessage.createSendMessage","qualifiedName":"im_flutter_sdk.EMMessage.createSendMessage","href":"im_flutter_sdk/EMMessage/EMMessage.createSendMessage.html","type":"constructor","overriddenDepth":0,"enclosedBy":{"name":"EMMessage","type":"class"}},{"name":"EMMessage.createTxtSendMessage","qualifiedName":"im_flutter_sdk.EMMessage.createTxtSendMessage","href":"im_flutter_sdk/EMMessage/EMMessage.createTxtSendMessage.html","type":"constructor","overriddenDepth":0,"enclosedBy":{"name":"EMMessage","type":"class"}},{"name":"EMMessage.createVideoSendMessage","qualifiedName":"im_flutter_sdk.EMMessage.createVideoSendMessage","href":"im_flutter_sdk/EMMessage/EMMessage.createVideoSendMessage.html","type":"constructor","overriddenDepth":0,"enclosedBy":{"name":"EMMessage","type":"class"}},{"name":"EMMessage.createVoiceSendMessage","qualifiedName":"im_flutter_sdk.EMMessage.createVoiceSendMessage","href":"im_flutter_sdk/EMMessage/EMMessage.createVoiceSendMessage.html","type":"constructor","overriddenDepth":0,"enclosedBy":{"name":"EMMessage","type":"class"}},{"name":"direction","qualifiedName":"im_flutter_sdk.EMMessage.direction","href":"im_flutter_sdk/EMMessage/direction.html","type":"property","overriddenDepth":0,"enclosedBy":{"name":"EMMessage","type":"class"}},{"name":"ext","qualifiedName":"im_flutter_sdk.EMMessage.ext","href":"im_flutter_sdk/EMMessage/ext.html","type":"method","overriddenDepth":0,"enclosedBy":{"name":"EMMessage","type":"class"}},{"name":"from","qualifiedName":"im_flutter_sdk.EMMessage.from","href":"im_flutter_sdk/EMMessage/from.html","type":"property","overriddenDepth":0,"enclosedBy":{"name":"EMMessage","type":"class"}},{"name":"hashCode","qualifiedName":"im_flutter_sdk.EMMessage.hashCode","href":"im_flutter_sdk/EMMessage/hashCode.html","type":"property","overriddenDepth":0,"enclosedBy":{"name":"EMMessage","type":"class"}},{"name":"localTime","qualifiedName":"im_flutter_sdk.EMMessage.localTime","href":"im_flutter_sdk/EMMessage/localTime.html","type":"property","overriddenDepth":0,"enclosedBy":{"name":"EMMessage","type":"class"}},{"name":"msgId","qualifiedName":"im_flutter_sdk.EMMessage.msgId","href":"im_flutter_sdk/EMMessage/msgId.html","type":"property","overriddenDepth":0,"enclosedBy":{"name":"EMMessage","type":"class"}},{"name":"msgTime","qualifiedName":"im_flutter_sdk.EMMessage.msgTime","href":"im_flutter_sdk/EMMessage/msgTime.html","type":"property","overriddenDepth":0,"enclosedBy":{"name":"EMMessage","type":"class"}},{"name":"noSuchMethod","qualifiedName":"im_flutter_sdk.EMMessage.noSuchMethod","href":"im_flutter_sdk/EMMessage/noSuchMethod.html","type":"method","overriddenDepth":0,"enclosedBy":{"name":"EMMessage","type":"class"}},{"name":"runtimeType","qualifiedName":"im_flutter_sdk.EMMessage.runtimeType","href":"im_flutter_sdk/EMMessage/runtimeType.html","type":"property","overriddenDepth":0,"enclosedBy":{"name":"EMMessage","type":"class"}},{"name":"status","qualifiedName":"im_flutter_sdk.EMMessage.status","href":"im_flutter_sdk/EMMessage/status.html","type":"property","overriddenDepth":0,"enclosedBy":{"name":"EMMessage","type":"class"}},{"name":"to","qualifiedName":"im_flutter_sdk.EMMessage.to","href":"im_flutter_sdk/EMMessage/to.html","type":"property","overriddenDepth":0,"enclosedBy":{"name":"EMMessage","type":"class"}},{"name":"type","qualifiedName":"im_flutter_sdk.EMMessage.type","href":"im_flutter_sdk/EMMessage/type.html","type":"property","overriddenDepth":0,"enclosedBy":{"name":"EMMessage","type":"class"}},{"name":"unread","qualifiedName":"im_flutter_sdk.EMMessage.unread","href":"im_flutter_sdk/EMMessage/unread.html","type":"property","overriddenDepth":0,"enclosedBy":{"name":"EMMessage","type":"class"}},{"name":"EMMessageListener","qualifiedName":"im_flutter_sdk.EMMessageListener","href":"im_flutter_sdk/EMMessageListener-class.html","type":"class","overriddenDepth":0,"enclosedBy":{"name":"im_flutter_sdk","type":"library"}},{"name":"EMMessageListener","qualifiedName":"im_flutter_sdk.EMMessageListener","href":"im_flutter_sdk/EMMessageListener/EMMessageListener.html","type":"constructor","overriddenDepth":0,"enclosedBy":{"name":"EMMessageListener","type":"class"}},{"name":"operator ==","qualifiedName":"im_flutter_sdk.EMMessageListener.==","href":"im_flutter_sdk/EMMessageListener/operator_equals.html","type":"method","overriddenDepth":0,"enclosedBy":{"name":"EMMessageListener","type":"class"}},{"name":"hashCode","qualifiedName":"im_flutter_sdk.EMMessageListener.hashCode","href":"im_flutter_sdk/EMMessageListener/hashCode.html","type":"property","overriddenDepth":0,"enclosedBy":{"name":"EMMessageListener","type":"class"}},{"name":"noSuchMethod","qualifiedName":"im_flutter_sdk.EMMessageListener.noSuchMethod","href":"im_flutter_sdk/EMMessageListener/noSuchMethod.html","type":"method","overriddenDepth":0,"enclosedBy":{"name":"EMMessageListener","type":"class"}},{"name":"onCmdMessageReceived","qualifiedName":"im_flutter_sdk.EMMessageListener.onCmdMessageReceived","href":"im_flutter_sdk/EMMessageListener/onCmdMessageReceived.html","type":"method","overriddenDepth":0,"enclosedBy":{"name":"EMMessageListener","type":"class"}},{"name":"onMessageChanged","qualifiedName":"im_flutter_sdk.EMMessageListener.onMessageChanged","href":"im_flutter_sdk/EMMessageListener/onMessageChanged.html","type":"method","overriddenDepth":0,"enclosedBy":{"name":"EMMessageListener","type":"class"}},{"name":"onMessageDelivered","qualifiedName":"im_flutter_sdk.EMMessageListener.onMessageDelivered","href":"im_flutter_sdk/EMMessageListener/onMessageDelivered.html","type":"method","overriddenDepth":0,"enclosedBy":{"name":"EMMessageListener","type":"class"}},{"name":"onMessageRead","qualifiedName":"im_flutter_sdk.EMMessageListener.onMessageRead","href":"im_flutter_sdk/EMMessageListener/onMessageRead.html","type":"method","overriddenDepth":0,"enclosedBy":{"name":"EMMessageListener","type":"class"}},{"name":"onMessageRecalled","qualifiedName":"im_flutter_sdk.EMMessageListener.onMessageRecalled","href":"im_flutter_sdk/EMMessageListener/onMessageRecalled.html","type":"method","overriddenDepth":0,"enclosedBy":{"name":"EMMessageListener","type":"class"}},{"name":"onMessageReceived","qualifiedName":"im_flutter_sdk.EMMessageListener.onMessageReceived","href":"im_flutter_sdk/EMMessageListener/onMessageReceived.html","type":"method","overriddenDepth":0,"enclosedBy":{"name":"EMMessageListener","type":"class"}},{"name":"runtimeType","qualifiedName":"im_flutter_sdk.EMMessageListener.runtimeType","href":"im_flutter_sdk/EMMessageListener/runtimeType.html","type":"property","overriddenDepth":0,"enclosedBy":{"name":"EMMessageListener","type":"class"}},{"name":"toString","qualifiedName":"im_flutter_sdk.EMMessageListener.toString","href":"im_flutter_sdk/EMMessageListener/toString.html","type":"method","overriddenDepth":0,"enclosedBy":{"name":"EMMessageListener","type":"class"}},{"name":"EMMessageType","qualifiedName":"im_flutter_sdk.EMMessageType","href":"im_flutter_sdk/EMMessageType-class.html","type":"enum","overriddenDepth":0,"enclosedBy":{"name":"im_flutter_sdk","type":"library"}},{"name":"operator ==","qualifiedName":"im_flutter_sdk.EMMessageType.==","href":"im_flutter_sdk/EMMessageType/operator_equals.html","type":"method","overriddenDepth":0,"enclosedBy":{"name":"EMMessageType","type":"enum"}},{"name":"hashCode","qualifiedName":"im_flutter_sdk.EMMessageType.hashCode","href":"im_flutter_sdk/EMMessageType/hashCode.html","type":"property","overriddenDepth":0,"enclosedBy":{"name":"EMMessageType","type":"enum"}},{"name":"noSuchMethod","qualifiedName":"im_flutter_sdk.EMMessageType.noSuchMethod","href":"im_flutter_sdk/EMMessageType/noSuchMethod.html","type":"method","overriddenDepth":0,"enclosedBy":{"name":"EMMessageType","type":"enum"}},{"name":"runtimeType","qualifiedName":"im_flutter_sdk.EMMessageType.runtimeType","href":"im_flutter_sdk/EMMessageType/runtimeType.html","type":"property","overriddenDepth":0,"enclosedBy":{"name":"EMMessageType","type":"enum"}},{"name":"toString","qualifiedName":"im_flutter_sdk.EMMessageType.toString","href":"im_flutter_sdk/EMMessageType/toString.html","type":"method","overriddenDepth":1,"enclosedBy":{"name":"EMMessageType","type":"enum"}},{"name":"EMMucSharedFile","qualifiedName":"im_flutter_sdk.EMMucSharedFile","href":"im_flutter_sdk/EMMucSharedFile-class.html","type":"class","overriddenDepth":0,"enclosedBy":{"name":"im_flutter_sdk","type":"library"}},{"name":"operator ==","qualifiedName":"im_flutter_sdk.EMMucSharedFile.==","href":"im_flutter_sdk/EMMucSharedFile/operator_equals.html","type":"method","overriddenDepth":0,"enclosedBy":{"name":"EMMucSharedFile","type":"class"}},{"name":"getFileId","qualifiedName":"im_flutter_sdk.EMMucSharedFile.getFileId","href":"im_flutter_sdk/EMMucSharedFile/getFileId.html","type":"method","overriddenDepth":0,"enclosedBy":{"name":"EMMucSharedFile","type":"class"}},{"name":"getFileName","qualifiedName":"im_flutter_sdk.EMMucSharedFile.getFileName","href":"im_flutter_sdk/EMMucSharedFile/getFileName.html","type":"method","overriddenDepth":0,"enclosedBy":{"name":"EMMucSharedFile","type":"class"}},{"name":"getFileOwner","qualifiedName":"im_flutter_sdk.EMMucSharedFile.getFileOwner","href":"im_flutter_sdk/EMMucSharedFile/getFileOwner.html","type":"method","overriddenDepth":0,"enclosedBy":{"name":"EMMucSharedFile","type":"class"}},{"name":"getFileSize","qualifiedName":"im_flutter_sdk.EMMucSharedFile.getFileSize","href":"im_flutter_sdk/EMMucSharedFile/getFileSize.html","type":"method","overriddenDepth":0,"enclosedBy":{"name":"EMMucSharedFile","type":"class"}},{"name":"getFileUpdateTime","qualifiedName":"im_flutter_sdk.EMMucSharedFile.getFileUpdateTime","href":"im_flutter_sdk/EMMucSharedFile/getFileUpdateTime.html","type":"method","overriddenDepth":0,"enclosedBy":{"name":"EMMucSharedFile","type":"class"}},{"name":"hashCode","qualifiedName":"im_flutter_sdk.EMMucSharedFile.hashCode","href":"im_flutter_sdk/EMMucSharedFile/hashCode.html","type":"property","overriddenDepth":0,"enclosedBy":{"name":"EMMucSharedFile","type":"class"}},{"name":"noSuchMethod","qualifiedName":"im_flutter_sdk.EMMucSharedFile.noSuchMethod","href":"im_flutter_sdk/EMMucSharedFile/noSuchMethod.html","type":"method","overriddenDepth":0,"enclosedBy":{"name":"EMMucSharedFile","type":"class"}},{"name":"runtimeType","qualifiedName":"im_flutter_sdk.EMMucSharedFile.runtimeType","href":"im_flutter_sdk/EMMucSharedFile/runtimeType.html","type":"property","overriddenDepth":0,"enclosedBy":{"name":"EMMucSharedFile","type":"class"}},{"name":"EMNormalFileMessageBody","qualifiedName":"im_flutter_sdk.EMNormalFileMessageBody","href":"im_flutter_sdk/EMNormalFileMessageBody-class.html","type":"class","overriddenDepth":0,"enclosedBy":{"name":"im_flutter_sdk","type":"library"}},{"name":"EMNormalFileMessageBody","qualifiedName":"im_flutter_sdk.EMNormalFileMessageBody","href":"im_flutter_sdk/EMNormalFileMessageBody/EMNormalFileMessageBody.html","type":"constructor","overriddenDepth":0,"enclosedBy":{"name":"EMNormalFileMessageBody","type":"class"}},{"name":"fileSize","qualifiedName":"im_flutter_sdk.EMNormalFileMessageBody.fileSize","href":"im_flutter_sdk/EMNormalFileMessageBody/fileSize.html","type":"property","overriddenDepth":0,"enclosedBy":{"name":"EMNormalFileMessageBody","type":"class"}},{"name":"EMOptions","qualifiedName":"im_flutter_sdk.EMOptions","href":"im_flutter_sdk/EMOptions-class.html","type":"class","overriddenDepth":0,"enclosedBy":{"name":"im_flutter_sdk","type":"library"}},{"name":"EMOptions","qualifiedName":"im_flutter_sdk.EMOptions","href":"im_flutter_sdk/EMOptions/EMOptions.html","type":"constructor","overriddenDepth":0,"enclosedBy":{"name":"EMOptions","type":"class"}},{"name":"operator ==","qualifiedName":"im_flutter_sdk.EMOptions.==","href":"im_flutter_sdk/EMOptions/operator_equals.html","type":"method","overriddenDepth":0,"enclosedBy":{"name":"EMOptions","type":"class"}},{"name":"allowChatRoomOwnerLeave","qualifiedName":"im_flutter_sdk.EMOptions.allowChatRoomOwnerLeave","href":"im_flutter_sdk/EMOptions/allowChatRoomOwnerLeave.html","type":"method","overriddenDepth":0,"enclosedBy":{"name":"EMOptions","type":"class"}},{"name":"appKey","qualifiedName":"im_flutter_sdk.EMOptions.appKey","href":"im_flutter_sdk/EMOptions/appKey.html","type":"property","overriddenDepth":0,"enclosedBy":{"name":"EMOptions","type":"class"}},{"name":"getAcceptInvitationAlways","qualifiedName":"im_flutter_sdk.EMOptions.getAcceptInvitationAlways","href":"im_flutter_sdk/EMOptions/getAcceptInvitationAlways.html","type":"method","overriddenDepth":0,"enclosedBy":{"name":"EMOptions","type":"class"}},{"name":"getAutoLogin","qualifiedName":"im_flutter_sdk.EMOptions.getAutoLogin","href":"im_flutter_sdk/EMOptions/getAutoLogin.html","type":"method","overriddenDepth":0,"enclosedBy":{"name":"EMOptions","type":"class"}},{"name":"getRequireAck","qualifiedName":"im_flutter_sdk.EMOptions.getRequireAck","href":"im_flutter_sdk/EMOptions/getRequireAck.html","type":"method","overriddenDepth":0,"enclosedBy":{"name":"EMOptions","type":"class"}},{"name":"getRequireDeliveryAck","qualifiedName":"im_flutter_sdk.EMOptions.getRequireDeliveryAck","href":"im_flutter_sdk/EMOptions/getRequireDeliveryAck.html","type":"method","overriddenDepth":0,"enclosedBy":{"name":"EMOptions","type":"class"}},{"name":"hashCode","qualifiedName":"im_flutter_sdk.EMOptions.hashCode","href":"im_flutter_sdk/EMOptions/hashCode.html","type":"property","overriddenDepth":0,"enclosedBy":{"name":"EMOptions","type":"class"}},{"name":"isAutoAcceptGroupInvitation","qualifiedName":"im_flutter_sdk.EMOptions.isAutoAcceptGroupInvitation","href":"im_flutter_sdk/EMOptions/isAutoAcceptGroupInvitation.html","type":"method","overriddenDepth":0,"enclosedBy":{"name":"EMOptions","type":"class"}},{"name":"isChatRoomOwnerLeaveAllowed","qualifiedName":"im_flutter_sdk.EMOptions.isChatRoomOwnerLeaveAllowed","href":"im_flutter_sdk/EMOptions/isChatRoomOwnerLeaveAllowed.html","type":"method","overriddenDepth":0,"enclosedBy":{"name":"EMOptions","type":"class"}},{"name":"isDeleteMessagesAsExitGroup","qualifiedName":"im_flutter_sdk.EMOptions.isDeleteMessagesAsExitGroup","href":"im_flutter_sdk/EMOptions/isDeleteMessagesAsExitGroup.html","type":"method","overriddenDepth":0,"enclosedBy":{"name":"EMOptions","type":"class"}},{"name":"isSortMessageByServerTime","qualifiedName":"im_flutter_sdk.EMOptions.isSortMessageByServerTime","href":"im_flutter_sdk/EMOptions/isSortMessageByServerTime.html","type":"method","overriddenDepth":0,"enclosedBy":{"name":"EMOptions","type":"class"}},{"name":"noSuchMethod","qualifiedName":"im_flutter_sdk.EMOptions.noSuchMethod","href":"im_flutter_sdk/EMOptions/noSuchMethod.html","type":"method","overriddenDepth":0,"enclosedBy":{"name":"EMOptions","type":"class"}},{"name":"runtimeType","qualifiedName":"im_flutter_sdk.EMOptions.runtimeType","href":"im_flutter_sdk/EMOptions/runtimeType.html","type":"property","overriddenDepth":0,"enclosedBy":{"name":"EMOptions","type":"class"}},{"name":"setAcceptInvitationAlways","qualifiedName":"im_flutter_sdk.EMOptions.setAcceptInvitationAlways","href":"im_flutter_sdk/EMOptions/setAcceptInvitationAlways.html","type":"method","overriddenDepth":0,"enclosedBy":{"name":"EMOptions","type":"class"}},{"name":"setAutoAcceptGroupInvitation","qualifiedName":"im_flutter_sdk.EMOptions.setAutoAcceptGroupInvitation","href":"im_flutter_sdk/EMOptions/setAutoAcceptGroupInvitation.html","type":"method","overriddenDepth":0,"enclosedBy":{"name":"EMOptions","type":"class"}},{"name":"setAutoLogin","qualifiedName":"im_flutter_sdk.EMOptions.setAutoLogin","href":"im_flutter_sdk/EMOptions/setAutoLogin.html","type":"method","overriddenDepth":0,"enclosedBy":{"name":"EMOptions","type":"class"}},{"name":"setDeleteMessagesAsExitGroup","qualifiedName":"im_flutter_sdk.EMOptions.setDeleteMessagesAsExitGroup","href":"im_flutter_sdk/EMOptions/setDeleteMessagesAsExitGroup.html","type":"method","overriddenDepth":0,"enclosedBy":{"name":"EMOptions","type":"class"}},{"name":"setRequireAck","qualifiedName":"im_flutter_sdk.EMOptions.setRequireAck","href":"im_flutter_sdk/EMOptions/setRequireAck.html","type":"method","overriddenDepth":0,"enclosedBy":{"name":"EMOptions","type":"class"}},{"name":"setRequireDeliveryAck","qualifiedName":"im_flutter_sdk.EMOptions.setRequireDeliveryAck","href":"im_flutter_sdk/EMOptions/setRequireDeliveryAck.html","type":"method","overriddenDepth":0,"enclosedBy":{"name":"EMOptions","type":"class"}},{"name":"setSortMessageByServerTime","qualifiedName":"im_flutter_sdk.EMOptions.setSortMessageByServerTime","href":"im_flutter_sdk/EMOptions/setSortMessageByServerTime.html","type":"method","overriddenDepth":0,"enclosedBy":{"name":"EMOptions","type":"class"}},{"name":"toString","qualifiedName":"im_flutter_sdk.EMOptions.toString","href":"im_flutter_sdk/EMOptions/toString.html","type":"method","overriddenDepth":0,"enclosedBy":{"name":"EMOptions","type":"class"}},{"name":"EMTextMessageBody","qualifiedName":"im_flutter_sdk.EMTextMessageBody","href":"im_flutter_sdk/EMTextMessageBody-class.html","type":"class","overriddenDepth":0,"enclosedBy":{"name":"im_flutter_sdk","type":"library"}},{"name":"EMTextMessageBody","qualifiedName":"im_flutter_sdk.EMTextMessageBody","href":"im_flutter_sdk/EMTextMessageBody/EMTextMessageBody.html","type":"constructor","overriddenDepth":0,"enclosedBy":{"name":"EMTextMessageBody","type":"class"}},{"name":"operator ==","qualifiedName":"im_flutter_sdk.EMTextMessageBody.==","href":"im_flutter_sdk/EMTextMessageBody/operator_equals.html","type":"method","overriddenDepth":0,"enclosedBy":{"name":"EMTextMessageBody","type":"class"}},{"name":"hashCode","qualifiedName":"im_flutter_sdk.EMTextMessageBody.hashCode","href":"im_flutter_sdk/EMTextMessageBody/hashCode.html","type":"property","overriddenDepth":0,"enclosedBy":{"name":"EMTextMessageBody","type":"class"}},{"name":"message","qualifiedName":"im_flutter_sdk.EMTextMessageBody.message","href":"im_flutter_sdk/EMTextMessageBody/message.html","type":"property","overriddenDepth":0,"enclosedBy":{"name":"EMTextMessageBody","type":"class"}},{"name":"noSuchMethod","qualifiedName":"im_flutter_sdk.EMTextMessageBody.noSuchMethod","href":"im_flutter_sdk/EMTextMessageBody/noSuchMethod.html","type":"method","overriddenDepth":0,"enclosedBy":{"name":"EMTextMessageBody","type":"class"}},{"name":"runtimeType","qualifiedName":"im_flutter_sdk.EMTextMessageBody.runtimeType","href":"im_flutter_sdk/EMTextMessageBody/runtimeType.html","type":"property","overriddenDepth":0,"enclosedBy":{"name":"EMTextMessageBody","type":"class"}},{"name":"EMVideoMessageBody","qualifiedName":"im_flutter_sdk.EMVideoMessageBody","href":"im_flutter_sdk/EMVideoMessageBody-class.html","type":"class","overriddenDepth":0,"enclosedBy":{"name":"im_flutter_sdk","type":"library"}},{"name":"EMVideoMessageBody","qualifiedName":"im_flutter_sdk.EMVideoMessageBody","href":"im_flutter_sdk/EMVideoMessageBody/EMVideoMessageBody.html","type":"constructor","overriddenDepth":0,"enclosedBy":{"name":"EMVideoMessageBody","type":"class"}},{"name":"length","qualifiedName":"im_flutter_sdk.EMVideoMessageBody.length","href":"im_flutter_sdk/EMVideoMessageBody/length.html","type":"property","overriddenDepth":0,"enclosedBy":{"name":"EMVideoMessageBody","type":"class"}},{"name":"EMVoiceMessageBody","qualifiedName":"im_flutter_sdk.EMVoiceMessageBody","href":"im_flutter_sdk/EMVoiceMessageBody-class.html","type":"class","overriddenDepth":0,"enclosedBy":{"name":"im_flutter_sdk","type":"library"}},{"name":"EMVoiceMessageBody","qualifiedName":"im_flutter_sdk.EMVoiceMessageBody","href":"im_flutter_sdk/EMVoiceMessageBody/EMVoiceMessageBody.html","type":"constructor","overriddenDepth":0,"enclosedBy":{"name":"EMVoiceMessageBody","type":"class"}},{"name":"length","qualifiedName":"im_flutter_sdk.EMVoiceMessageBody.length","href":"im_flutter_sdk/EMVoiceMessageBody/length.html","type":"property","overriddenDepth":0,"enclosedBy":{"name":"EMVoiceMessageBody","type":"class"}},{"name":"EMVoiceMessageBody.of","qualifiedName":"im_flutter_sdk.EMVoiceMessageBody.of","href":"im_flutter_sdk/EMVoiceMessageBody/EMVoiceMessageBody.of.html","type":"constructor","overriddenDepth":0,"enclosedBy":{"name":"EMVoiceMessageBody","type":"class"}}]
